<DOMSymbolItem xmlns:xsi="http://www.w3.org/2001/XMLSchema-instance" xmlns="http://ns.adobe.com/xfl/2008/" name="Assets/CCalendarTime Assets/CCalendarNewBlank" itemID="5afdbf14-00000b2c" lastModified="1526579838">
  <timeline>
    <DOMTimeline name="CCalendarNewBlank">
      <layers>
        <DOMLayer name="Layer_1" color="#00FFFF" current="true" isSelected="true">
          <frames>
            <DOMFrame index="0" keyMode="9728">
              <elements>
                <DOMShape>
                  <fills>
                    <FillStyle index="1">
                      <SolidColor color="#FFFFFF"/>
                    </FillStyle>
                    <FillStyle index="2">
                      <SolidColor color="#D72A2B"/>
                    </FillStyle>
                    <FillStyle index="3">
                      <SolidColor color="#999999" alpha="0.498039215686275"/>
                    </FillStyle>
                    <FillStyle index="4">
                      <SolidColor color="#666666" alpha="0.498039215686275"/>
                    </FillStyle>
                  </fills>
                  <strokes>
                    <StrokeStyle index="1">
                      <SolidStroke scaleMode="normal">
                        <fill>
                          <SolidColor color="#999999"/>
                        </fill>
                      </SolidStroke>
                    </StrokeStyle>
                    <StrokeStyle index="2">
                      <SolidStroke scaleMode="normal">
                        <fill>
                          <SolidColor color="#666666"/>
                        </fill>
                      </SolidStroke>
                    </StrokeStyle>
                  </strokes>
                  <edges>
                    <Edge fillStyle1="1" edges="!436 -317[441 -317 442 -315!442 -315[443 -314 447 -310!447 -310[450 -306 453 -307!453 -307|452 -139!452 -139[438 -123 428 -120!428 -120[419 -118 415 -117!415 -117[327 -109 240 -120!240 -120|239 -168!239 -168[237 -174 230 -174!230 -174
[230 -176 227 -185!227 -185[224 -192 224 -205!224 -205|225 -338!225 -338|277 -336!277 -336[278 -335 279 -333!279 -333[350 -331 432 -326!432 -326|432 -317!432 -317|436 -317!186 -334[194 -330 196 -326!196 -326[200 -322 200 -314!200 -314
[202 -306 200 -298!200 -298[200 -289 196 -287!196 -287[191 -282 182 -288!182 -288[180 -290 175 -302!175 -302[173 -312 168 -317!168 -317[159 -314 149 -314!149 -314[137 -314 131 -320!131 -320[126 -323 126 -329!126 -329|126 -331!126 -331
[126 -336 129 -339!129 -339[131 -342 136 -342!136 -342|135 -343!135 -343|173 -342!173 -342|180 -341!180 -341[184 -338 185 -334!185 -334|186 -334!120 91[115 91 79 91!79 91[40 92 34 92!34 92[28 92 22 91!22 91|22 96!22 96[17 102 4 102!4
 102|-50 100!-50 100|-50 -39!-50 -39[-48 -39 -46 -38!-46 -38|-46 -49!-46 -49[-40 -47 -40 -54!-40 -54|-30 -55!-30 -55|-30 -82!-30 -82|11 -85!11 -85[18 -85 15 -88!15 -88[43 -89 82 -84!82 -84|107 -78!107 -78|192 -77!192 -77[192 -73 194 -66
!194 -66|202 -66!202 -66|203 72!203 72[200 74 197 75!197 75|197 86!197 86|138 88!138 88[130 90 120 91!354 85[313 88 297 87!297 87[289 87 282 85!282 85|282 87!282 87|219 86!219 86|220 -53!220 -53|224 -54!224 -54|224 -88!224 -88[265 -92
 336 -80!336 -80[376 -73 404 -69!404 -69|404 -78!404 -78|458 -76!458 -76|458 66!458 66|447 66!447 66|447 72!447 72[431 72 416 72!416 72[413 73 409 75!409 75[398 80 354 85"/>
                    <Edge strokeStyle="1" edges="
!210 -353|210 -103"/>
                    <Edge fillStyle1="1" edges="
!729 -145[731 -134 727 -125!727 -125[722 -115 712 -111!712 -111[703 -106 692 -110!692 -110[682 -114 678 -124!678 -124[675 -131 675 -145!675 -145[671 -143 668 -140!668 -140|668 -113!668 -113[631 -105 560 -115!560 -115|560 -122!560 -122
[557 -123 555 -124!555 -124|552 -124!552 -124[548 -124 544 -124!544 -124|485 -125!485 -125|485 -161!485 -161|475 -165!475 -165|474 -333!474 -333[523 -334 562 -331!562 -331|565 -333!565 -333|659 -332!659 -332[670 -332 676 -331!676 -331
|683 -328!683 -328|683 -329!683 -329[686 -337 694 -341!694 -341[701 -345 708 -342!708 -342[720 -336 720 -313!720 -313[722 -244 719 -209!719 -209[718 -205 718 -201!718 -201[716 -184 718 -173!718 -173[718 -171 719 -169!719 -169[722 -160
 729 -145"/>
                    <Edge strokeStyle="1" edges="
!450 -353|453 -307!453 -307|460 -198"/>
                    <Edge fillStyle1="1" edges="
!558 77[541 77 528 75!528 75[526 88 522 96!522 96|470 95!470 95|469 -47!469 -47[469 -62 475 -68!475 -68|499 -67!499 -67|499 -78!499 -78[569 -78 633 -75!633 -75|641 -80!641 -80[672 -102 708 -87!708 -87[743 -72 749 -35!749 -35[752 -23 750
 -8!750 -8[745 12 743 16!743 16[739 26 728 37!728 37[718 46 698 56!698 56[695 57 693 59!693 59|693 67!693 67[684 67 676 67!676 67[674 67 672 68!672 68[661 71 640 73!640 73[604 77 558 77"/>
                    <Edge strokeStyle="1" edges="
!460 -198|460 -103"/>
                    <Edge fillStyle0="1" strokeStyle="1" edges="
!450 -353|770 -353!770 -353|770 -103"/>
                    <Edge strokeStyle="1" edges="
!460 -103|770 -103!460 -293|460 -198!210 -103|460 -103"/>
                    <Edge fillStyle0="1" strokeStyle="1" edges="
!210 -353|450 -353"/>
                    <Edge fillStyle0="1" fillStyle1="2" strokeStyle="2" edges="
!1021 -560[1020 -523 981 -523!981 -523|-981 -523!-981 -523[-1020 -523 -1021 -560"/>
                    <Edge fillStyle1="2" strokeStyle="2" edges="
!-1021 -560|-1021 -984!-1021 -984[-1021 -1024 -981 -1024!-981 -1024|981 -1024!981 -1024[1021 -1024 1021 -984!1021 -984|1021 -560"/>
                    <Edge fillStyle1="1" edges="
!938 37|939 37!939 37[939 32 939 28!939 28[924 40 921 51!921 51[919 58 918 70!918 70[930 51 938 37!846 237[844 238 843 239!843 239[841 240 839 241!839 241[839 251 819 259!819 259[811 263 803 268!803 268[801 271 799 273!799 273[798 274
 798 276!798 276[798 280 799 288!799 288[804 287 808 293"/>
                    <Edge fillStyle0="1" fillStyle1="3" edges="
!846 237[854 223 859 211!859 211[861 208 863 205!863 205[876 180 889 173!889 173[903 146 920 147!920 147[945 148 949 187!949 187[950 215 944 247!944 247[934 303 914 359!914 359[887 428 852 463!852 463[844 471 836 478!836 478[838 483 837
 489!837 489[836 502 823 513!823 513[816 519 798 525!798 525[777 533 753 536!753 536[746 537 740 537!740 537[732 537 725 537!550 953[540 957 530 961!530 961[463 986 411 987!411 987[391 989 377 982!377 982[358 970 359 954!359 954[360 937
 382 929!382 929[393 925 416 923!416 923[450 920 502 901!502 901[538 888 560 875!560 875[580 864 614 834!614 834|681 777!681 777[720 742 733 727!733 727[746 713 759 693!759 693|821 606!821 606[823 603 825 601!825 601[850 564 862 544!862
 544[863 540 865 537!865 537[886 497 891 461!891 461[892 444 893 435!893 435[895 420 900 410!900 410[906 397 918 391!918 391[931 384 942 390!942 390[957 398 957 417!957 417[958 427 954 449!954 449|944 501!944 501[939 523 925 552"/>
                    <Edge fillStyle0="1" fillStyle1="4" edges="
!925 552[930 558 930 574!930 574|929 836!929 836[929 863 926 876!926 876[921 893 911 905!911 905[886 934 824 946!824 946[784 955 756 956!756 956|550 953"/>
                    <Edge fillStyle0="4" fillStyle1="3" edges="
!925 552[914 574 898 600!898 600[887 618 874 637!874 637|873 638!873 638[878 636 883 637!883 637[895 638 901 650!901 650[907 661 905 673!905 673[903 687 882 715!882 715|821 787!821 787[768 850 730 873!730 873[708 886 691 886!691 886[679
 885 672 880"/>
                    <Edge fillStyle0="1" fillStyle1="3" edges="
!414 750[410 765 405 778!405 778[402 788 388 817!388 817[373 847 361 881!361 881[352 902 345 925!345 925[343 930 342 935!342 935[#14E.A3 #3B8.7D 325.5 960!325.5 960|325 960!325 960[324 960 324 961!324 961[322 961 321 963!321 963|320.5
 963!320.5 963[#13D.E5 #3C3.0D 316 964!316 964[311 965 306 965!306 965[290 980 275 983!275 983[253 987 242 970!242 970[238 963 239 956!239 956[239 946 245 934!245 934[249 927 256 918!256 918[267 906 269 903!269 903[286 881 300 823!300
 823|317 757"/>
                    <Edge fillStyle1="3" edges="
!317 757|317 754!317 754[336 670 339 646!339 646[349 580 353 564!353 564[359 544 368 529!368 529[378 509 393 496!393 496[416 476 456 468!456 468[457 468 460 467!460 467[474 465 528 458!528 458[574 452 616 439"/>
                    <Edge strokeStyle="1" edges="
!460 337|460 467"/>
                    <Edge fillStyle1="1" edges="
!616 439[615 439 614 439!614 439|609 431!609 431[613 425 624 423!624 423|652 417!652 417|660 405!660 405[657 406 654 406!654 406[632 408 622 414!622 414|610 423!610 423|597 424!597 424[576 424 569 415!569 415[571 409 589 404!589 404[591
 404 612 393!612 393[623 387 654 381!654 381|650 375!650 375[650 367 660 367!660 367|660 365!660 365|686 366!686 366|689 361!689 361[698 348 706 337!706 337[715 323 723 312!723 312[717 305 714 301!714 301[708 295 709 287!709 287[711 278
 720 278!720 278[724 278 730 284!730 284|732 286!732 286|733 285!733 285|739 285!739 285|742 286!742 286|743 287!743 287[756 271 770 259!775 297[777 296 780 295!780 295[780 289 780 285!780 285[780 284 779 284!779 284[775 288 770 292!770
 292[762 300 753 308!753 308[756 312 757 315!757 315|759 321!759 321[759 322 758 325!758 325[766 318 768 313!768 313[769 310 770 308!770 308[773 299 775 297"/>
                    <Edge fillStyle0="1" strokeStyle="1" edges="
!770 107|770 259"/>
                    <Edge fillStyle0="1" fillStyle1="1" strokeStyle="1" edges="
!770 259|770 292"/>
                    <Edge strokeStyle="1" edges="
!770 292|770 308"/>
                    <Edge fillStyle0="1" fillStyle1="1" strokeStyle="1" edges="
!770 308|770 337"/>
                    <Edge fillStyle0="1" fillStyle1="3" edges="
!766 347[768 344 770 342!770 342[785 324 802 300!802 300[805 296 808 293"/>
                    <Edge fillStyle1="1" edges="
!744 334[737 334 733 330!733 330[731 334 729 337!729 337[727 339 726 340!726 340[730 338 734 337!734 337[737 336 741 336!741 336[742 335 744 334"/>
                    <Edge strokeStyle="1" edges="
!460 337|706 337"/>
                    <Edge fillStyle0="1" fillStyle1="1" strokeStyle="1" edges="
!706 337|729 337"/>
                    <Edge strokeStyle="1" edges="
!729 337|734 337"/>
                    <Edge fillStyle0="1" fillStyle1="1" strokeStyle="1" edges="
!734 337|770 337"/>
                    <Edge fillStyle1="1" edges="
!766 347[762 348 760 349!760 349[756 351 750 356!750 356|749 357!749 357|749 358!749 358[749 363 747 368"/>
                    <Edge fillStyle0="1" fillStyle1="1" strokeStyle="1" edges="
!770 337|770 342"/>
                    <Edge fillStyle1="3" edges="
!747 368[756 359 766 347"/>
                    <Edge fillStyle0="1" fillStyle1="3" edges="
!616 439[632 434 648 428!648 428[708 403 739 375!739 375[743 372 747 368"/>
                    <Edge strokeStyle="1" edges="
!460 107|770 107!460 107|460 337!210 107|210 337!210 531|368 529"/>
                    <Edge fillStyle0="1" strokeStyle="1" edges="
!317 757|210 757"/>
                    <Edge strokeStyle="1" edges="
!210 531|210 757"/>
                    <Edge fillStyle1="3" edges="
!725 537[712 536 704 531!704 531[694 537 675 537!675 537|627 539"/>
                    <Edge fillStyle1="1" edges="
!627 539[624 542 622 545!622 545[630 543 638 543!638 543[686 538 725 537"/>
                    <Edge fillStyle1="3" edges="
!556 542|545 542!545 542[518 547 479 584!479 584[458 604 452 619!452 619|445 645!445 645[442 653 433 667!433 667[428 679 426 694!426 694|417 738!417 738[416 744 414 750"/>
                    <Edge fillStyle1="1" edges="
!563 562[560 564 557 567!557 567[571 560 580 555!580 555[572 559 563 562!414 750[424 738 433 729!433 729[442 719 451 716!451 716[458 683 478 655!478 655[489 641 496 633!496 633[499 627 501 623!501 623[501 622 502 622!502 622[510 594 517
 581!517 581[526 564 556 542!412 791[414 786 417 782!417 782[409 791 402 801!402 801|412 791"/>
                    <Edge fillStyle0="4" fillStyle1="3" edges="
!653 884[641 895 631 903!631 903[629 904 628 906!628 906[612 919 599 927!599 927[576 942 550 953"/>
                    <Edge fillStyle1="4" edges="
!653 884[658 883 666 883!666 883[669 882 672 880"/>
                    <Edge fillStyle1="3" edges="
!672 880[668 877 665 873!665 873[659 879 653 884"/>
                    <Edge fillStyle1="4" edges="
!642 929|640 929!640 929[637 929 637 932!637 932|671 932!671 932|642 929"/>
                    <Edge fillStyle0="1" fillStyle1="3" edges="
!627 539|556 542"/>
                    <Edge strokeStyle="1" edges="
!210 337|460 337!210 337|210 531!210 107|460 107"/>
                    <Edge fillStyle1="1" strokeStyle="2" edges="
!1021 -560|1021 975!1021 975[1021 1015 981 1015!981 1015|288 1015"/>
                    <Edge fillStyle0="1" fillStyle1="1" strokeStyle="2" edges="
!288 1015|271 1015"/>
                    <Edge fillStyle1="1" strokeStyle="2" edges="
!271 1015|-981 1015!-981 1015[-1021 1015 -1021 975!-1021 975|-1021 -560"/>
                    <Edge fillStyle1="1" edges="
!288 1015[283 1021 275 1024!275 1024[271 1021 271 1015"/>
                    <Edge fillStyle1="3" edges="
!808 293[831 261 846 237"/>
                    <Edge strokeStyle="1" edges="
!460 -103|460 107!210 -103|210 107"/>
                    <Edge fillStyle0="1" strokeStyle="1" edges="
!770 -103|770 107"/>
                    <Edge fillStyle1="1" edges="
!-344 -332[-334 -328 -334 -322!-334 -322[-334 -320 -339 -311!-339 -311[-338 -305 -337 -297!-337 -297[-328 -235 -342 -171!-342 -171[-334 -168 -331 -157!-331 -157[-330 -148 -333 -138!-333 -138[-338 -123 -348 -118!-348 -118[-361 -110 -375
 -116!-375 -116[-393 -122 -396 -141!-396 -141[-397 -150 -396 -160!-396 -160|-395 -185!-395 -185[-393 -208 -389 -218!-389 -218[-383 -229 -380 -235!-380 -235[-382 -240 -385 -248!-385 -248[-391 -262 -390 -272!-390 -272[-406 -272 -410 -274
!-410 -274[-415 -276 -417 -280!-417 -280[-420 -286 -419 -290!-419 -290[-418 -295 -410 -299!-410 -299[-408 -300 -404 -302!-404 -302[-412 -308 -413 -316!-413 -316[-414 -326 -405 -333!-405 -333[-397 -339 -385 -341!-385 -341[-369 -345 -358
 -339!-358 -339[-353 -337 -350 -333!-350 -333|-344 -332"/>
                    <Edge strokeStyle="1" edges="
!-740 -103|-520 -103"/>
                    <Edge fillStyle0="1" strokeStyle="1" edges="
!-740 -103|-740 -353!-740 -353|-300 -353"/>
                    <Edge fillStyle1="1" edges="
!-360 -450|-253 -446!-253 -446[-252 -454 -250 -462!-250 -462[-247 -469 -243 -475!-243 -475|-272 -474!-272 -474[-268 -467 -276 -461!-276 -461[-280 -459 -290 -459!-290 -459|-359 -459!-359 -459[-359 -454 -360 -450!-285 -404|-246 -401!-246
 -401[-248 -405 -249 -408!-249 -408[-267 -403 -285 -404!-387 29[-392 20 -389 3!-389 3[-386 -17 -385 -23!-385 -23[-385 -24 -385 -25!-385 -25[-388 -42 -389 -51!-389 -51[-389 -52 -389 -53!-389 -53[-394 -55 -399 -57!-399 -57[-412 -62 -408
 -76!-408 -76[-406 -89 -393 -92!-393 -92[-390 -92 -389 -94!-389 -94|-364 -94!-364 -94[-348 -94 -340 -86!-340 -86[-333 -79 -336 -69!-336 -69[-338 -59 -346 -56!-346 -56|-347 -55!-347 -55[-346 -48 -345 -41!-345 -41[-327 -40 -308 -36!-308
 -36|-308 101!-308 101|-375 101!-375 101[-379 101 -384 98!-384 98|-386 90!-386 90|-385 32!-385 32[-386 30 -387 29!-291 -48|-68 -47!-68 -47|-67 92!-67 92|-142 92!-142 92|-142 96!-142 96|-285 96!-285 96|-285 90!-285 90|-290 90!-290 90|-291
 -48"/>
                    <Edge fillStyle0="1" strokeStyle="1" edges="
!-300 -353|-60 -353"/>
                    <Edge strokeStyle="1" edges="
!-300 -103|-60 -103!-60 -353|-60 -103!-300 -353|-300 -103!-520 -103|-300 -103!-300 107|-300 337"/>
                    <Edge fillStyle1="1" edges="
!-317 118|-318 257!-318 257[-381 256 -505 250!-505 250|-505 112!-505 112[-412 111 -317 118"/>
                    <Edge strokeStyle="1" edges="
!-300 337|-60 337!-300 107|-60 107!-60 107|-60 337"/>
                    <Edge fillStyle1="1" edges="
!-684 206[-684 207 -684 209!-684 209[-684 214 -685 220!-685 220[-685 232 -688 237!-688 237[-692 245 -702 246!-702 246[-711 247 -717 241!-717 241[-723 235 -725 209!-725 209[-725 201 -728 181!-728 181[-731 162 -730 152!-730 152[-728 140
 -724 135!-724 135[-720 129 -709 127!-709 127[-699 129 -694 135!-694 135[-696 127 -686 122!-686 122[-678 117 -666 117!-666 117[-619 114 -565 123!-565 123|-562 117!-562 117[-557 112 -550 114!-550 114|-550 112!-550 112[-537 112 -531 125
!-531 125[-530 130 -530 135!-530 135[-524 140 -525 147!-525 147[-525 155 -538 166!-538 166[-551 177 -562 182!-562 182[-573 187 -600 187!-600 187[-654 187 -684 184!-684 184|-684 206"/>
                    <Edge fillStyle0="1" strokeStyle="1" edges="
!-740 337|-740 107"/>
                    <Edge strokeStyle="1" edges="
!-740 337|-520 337!-520 107|-520 337!-740 107|-520 107"/>
                    <Edge fillStyle0="1" strokeStyle="1" edges="
!-520 757|-740 757!-740 757|-740 547"/>
                    <Edge strokeStyle="1" edges="
!-520 544|-520 757!-740 547|-520 544!-60 536|-60 757!-300 540|-60 536"/>
                    <Edge fillStyle0="1" strokeStyle="1" edges="
!-60 757|-300 757"/>
                    <Edge strokeStyle="1" edges="
!-300 540|-300 757"/>
                    <Edge fillStyle0="1" strokeStyle="1" edges="
!-740 547|-740 337"/>
                    <Edge strokeStyle="1" edges="
!-60 337|-60 536"/>
                    <Edge fillStyle0="1" strokeStyle="1" edges="
!-300 757|-520 757"/>
                    <Edge strokeStyle="1" edges="
!-300 337|-300 540!-520 337|-520 544!-520 544|-300 540!-520 337|-300 337!-520 107|-300 107"/>
                    <Edge fillStyle0="1" strokeStyle="1" edges="
!-740 107|-740 -103"/>
                    <Edge strokeStyle="1" edges="
!-60 -103|-60 107!-520 -103|-520 107!-300 -103|-300 107"/>
                    <Edge fillStyle0="1" strokeStyle="1" edges="
!-60 -353|210 -353!210 757|-60 757"/>
                    <Edge strokeStyle="1" edges="
!-60 536|210 531!-60 337|210 337!-60 107|210 107!-60 -103|210 -103"/>
                    <Edge cubics="!786 586(;775,587 763,589 751,590p786 586 751 590);"/>
                    <Edge cubics="!751 590(;737,591 724,593 711,592q751 590Q717 592q711 592);"/>
                    <Edge cubics="!830 535(;837,535 845,539 847,547q830 535Q844 535q847 547);"/>
                    <Edge cubics="!949 68(;933,96 917,124 902,152p949 68 902 152);"/>
                    <Edge cubics="!806 200(;814,184 821,167 829,150q806 200 829 150);"/>
                    <Edge cubics="!829 150(;833,141 838,131 847,128q829 150Q837 131q847 128);"/>
                    <Edge cubics="!908 -40(;908,-53 930,-58 936,-47q908 -40Q908 -50q920 -52Q931 -55q936 -47);"/>
                    <Edge cubics="!936 -47(;941,-38 939,-22 950,-22q936 -47Q936 -47q941 -31Q943 -22q950 -22);"/>
                    <Edge cubics="!950 -22(;948,-31 951,-44 961,-46q950 -22Q948 -30q951 -37Q954 -45q961 -46);"/>
                    <Edge cubics="!961 -46(;962,-38 975,-42 978,-50q961 -46Q962 -40q969 -42Q976 -44q978 -50);"/>
                    <Edge cubics="!997 36(;994,42 983,44 980,38q997 36Q995 41q989 42Q982 42q980 38);"/>
                    <Edge cubics="!980 38(;956,61 984,109 960,133q980 38Q968 50q970 85Q972 121q960 133);"/>
                    <Edge cubics="!960 133(;957,131 953,129 950,127q960 133 950 127);"/>
                    <Edge cubics="!950 127(;949,108 949,88 949,68q950 127 949 68);"/>
                    <Edge cubics="!885 106(;891,93 896,81 898,67q885 106Q896 83q898 67);"/>
                    <Edge cubics="!898 67(;900,56 899,45 903,35q898 67Q899 45q903 35);"/>
                    <Edge cubics="!980 -62(;980,-77 980,-93 979,-108q980 -62 979 -108);"/>
                    <Edge cubics="!979 -108(;979,-113 979,-119 984,-122q979 -108Q979 -119q984 -122);"/>
                    <Edge cubics="!984 -122(;988,-124 993,-122 996,-118q984 -122Q991 -125q996 -118);"/>
                    <Edge cubics="!996 -118(;998,-114 999,-109 999,-104q996 -118Q999 -112q999 -104);"/>
                    <Edge cubics="!597 424(;587,424 575,423 569,415q597 424Q576 424q569 415);"/>
                    <Edge cubics="!569 415(;571,407 581,406 589,404q569 415Q571 409q589 404);"/>
                    <Edge cubics="!589 404(;597,402 604,397 612,393q589 404Q591 404q612 393);"/>
                    <Edge cubics="!654 406(;643,407 632,408 622,414q654 406Q632 408q622 414);"/>
                    <Edge cubics="!622 414(;618,417 615,421 610,423q622 414Q610 423q610 423);"/>
                    <Edge cubics="!610 423(;606,424 601,424 597,424q610 423 597 424);"/>
                    <Edge cubics="!757 315(;758,317 759,319 759,321p757 315 759 321);"/>
                    <Edge cubics="!744 334(;740,334 736,333 733,330q744 334Q737 334q733 330);"/>
                    <Edge cubics="!714 301(;710,297 708,292 709,287q714 301Q708 295q709 287);"/>
                    <Edge cubics="!709 287(;710,282 715,278 720,278q709 287Q711 278q720 278);"/>
                    <Edge cubics="!720 278(;724,278 727,281 730,284q720 278Q724 278q730 284);"/>
                    <Edge cubics="!660 367(;660,366 660,366 660,365p660 367 660 365);"/>
                    <Edge cubics="!650 375(;650,370 655,367 660,367q650 375Q650 367q660 367);"/>
                    <Edge cubics="!380 895(;390,881 391,862 395,844q380 895Q386 886q390 871Q393 853q395 844);"/>
                    <Edge cubics="!531 659(;520,674 506,687 494,701q531 659Q520 674q494 701);"/>
                    <Edge cubics="!405 903(;396,906 385,903 380,895q405 903Q388 909q380 895);"/>
                    <Edge cubics="!488 794(;486,797 484,800 482,803p488 794 482 803);"/>
                    <Edge cubics="!482 803(;473,802 464,802 455,802p482 803 455 802);"/>
                    <Edge cubics="!469 783(;477,784 484,788 488,794q469 783Q482 785q488 794);"/>
                    <Edge cubics="!433 729(;438,723 444,718 451,716q433 729Q442 719q451 716);"/>
                    <Edge cubics="!338 994(;338,1000 329,1002 323,1003q338 994Q338 1001q323 1003);"/>
                    <Edge cubics="!164 1011(;159,1001 154,991 149,981q164 1011 149 981);"/>
                    <Edge cubics="!149 981(;164,973 182,969 200,970q149 981Q173 969q200 970);"/>
                    <Edge cubics="!200 970(;198,965 201,959 206,957q200 970Q196 961q206 957);"/>
                    <Edge cubics="!206 957(;211,955 216,955 222,955q206 957Q211 955q222 955);"/>
                    <Edge cubics="!614 439(;613,437 611,434 609,431q614 439 609 431);"/>
                    <Edge cubics="!609 431(;612,426 618,424 624,423q609 431Q613 425q624 423);"/>
                    <Edge cubics="!1000 -78(;1006,-79 1013,-76 1016,-70q1000 -78Q1011 -80q1016 -70);"/>
                    <Edge cubics="!1016 -70(;1019,-65 1019,-59 1019,-53q1016 -70Q1019 -65q1019 -53);"/>
                    <Edge cubics="!1019 -53(;1020,-35 1020,-18 1020,0q1019 -53 1020 0);"/>
                    <Edge cubics="!1020 0(;1020,10 1019,22 1013,30q1020 0Q1020 21q1013 30);"/>
                    <Edge cubics="!1013 30(;1010,30 1007,30 1004,29q1013 30 1004 29);"/>
                    <Edge cubics="!945 496(;950,496 955,497 959,499q945 496Q953 496q959 499);"/>
                    <Edge cubics="!959 499(;966,502 971,506 975,511q959 499Q969 503q975 511);"/>
                    <Edge cubics="!975 511(;980,518 983,525 988,531q975 511 988 531);"/>
                    <Edge cubics="!988 531(;993,538 999,542 1004,549q988 531 1004 549);"/>
                    <Edge cubics="!1004 549(;1012,562 1011,578 1009,593q1004 549Q1013 564q1009 593);"/>
                    <Edge cubics="!1009 593(;1009,600 1007,608 1001,610q1009 593Q1009 607q1001 610);"/>
                    <Edge cubics="!1001 610(;994,613 985,607 978,610q1001 610Q998 612q990 610Q982 609q978 610);"/>
                    <Edge cubics="!978 610(;983,617 982,627 977,633q978 610Q986 622q977 633);"/>
                    <Edge cubics="!977 633(;972,639 963,642 955,639q977 633Q968 644q955 639);"/>
                    <Edge cubics="!955 639(;940,633 938,613 940,596q955 639Q936 631q940 596);"/>
                    <Edge cubics="!803 599(;800,599 798,599 796,598q803 599 796 598);"/>
                    <Edge cubics="!821 29(;812,3 816,-25 820,-52q821 29Q812 3q820 -52);"/>
                    <Edge cubics="!820 -52(;835,-162 850,-273 866,-383q820 -52 866 -383);"/>
                    <Edge cubics="!866 -383(;866,-389 868,-395 873,-396q866 -383Q866 -395q873 -396);"/>
                    <Edge cubics="!873 -396(;881,-398 884,-386 883,-377q873 -396Q879 -397q881 -391Q884 -385q883 -377);"/>
                    <Edge cubics="!883 -377(;867,-248 850,-120 834,9q883 -377 834 9);"/>
                    <Edge cubics="!834 9(;849,8 865,13 877,23q834 9Q858 7q877 23);"/>
                    <Edge cubics="!877 23(;859,30 840,33 821,29q877 23Q847 35q821 29);"/>
                    <Edge cubics="!733 285(;735,285 737,284 739,285q733 285Q739 285q739 285);"/>
                    <Edge cubics="!739 285(;740,285 741,286 742,286q739 285 742 286);"/>
                    <Edge cubics="!939 28(;929,36 923,44 921,51q939 28Q924 40q921 51);"/>
                    <Edge cubics="!939 37(;939,34 939,31 939,28q939 37Q939 32q939 28);"/>
                    <Edge cubics="!938 37(;938,37 939,37 939,37q938 37 939 37);"/>
                    <Edge cubics="!903 35(;908,25 919,15 937,5q903 35Q910 20q937 5);"/>
                    <Edge cubics="!937 5(;933,-14 923,-29 908,-40q937 5Q931 -24q908 -40);"/>
                    <Edge cubics="!732 286(;732,286 733,285 733,285q732 286 733 285);"/>
                    <Edge cubics="!730 284(;730,284 732,286 732,286q730 284 732 286);"/>
                    <Edge cubics="!742 286(;742,286 742,286 743,287q742 286Q742 286q743 287);"/>
                    <Edge cubics="!723 312(;719,307 716,304 714,301q723 312Q717 305q714 301);"/>
                    <Edge cubics="!884 162(;882,165 880,168 878,170q884 162Q881 167q878 170);"/>
                    <Edge cubics="!902 152(;895,162 889,165 884,162q902 152Q891 167q884 162);"/>
                    <Edge cubics="!868 128(;871,128 873,128 875,128q868 128Q872 128q875 128);"/>
                    <Edge cubics="!875 128(;875,128 885,106 885,106q875 128 885 106);"/>
                    <Edge cubics="!843 239(;842,240 840,240 839,241q843 239Q841 240q839 241);"/>
                    <Edge cubics="!801 235(;798,226 800,214 806,200q801 235Q797 221q806 200);"/>
                    <Edge cubics="!799 237(;799,237 801,235 801,235q799 237 801 235);"/>
                    <Edge cubics="!803 268(;802,270 800,272 799,273q803 268Q801 271q799 273);"/>
                    <Edge cubics="!799 273(;798,274 798,275 798,276q799 273Q798 274q798 276);"/>
                    <Edge cubics="!780 285(;780,284 780,284 779,284q780 285Q780 284q779 284);"/>
                    <Edge cubics="!780 295(;780,291 780,288 780,285q780 295Q780 289q780 285);"/>
                    <Edge cubics="!775 297(;776,296 778,296 780,295q775 297Q777 296q780 295);"/>
                    <Edge cubics="!798 276(;798,279 798,283 799,288q798 276Q798 280q799 288);"/>
                    <Edge cubics="!819 259(;814,262 808,265 803,268q819 259Q811 263q803 268);"/>
                    <Edge cubics="!839 241(;839,248 832,254 819,259q839 241Q839 251q819 259);"/>
                    <Edge cubics="!847 128(;850,127 857,127 868,128q847 128Q852 126q868 128);"/>
                    <Edge cubics="!921 51(;920,56 919,62 918,70q921 51Q919 58q918 70);"/>
                    <Edge cubics="!918 70(;926,57 933,46 938,37q918 70Q930 51q938 37);"/>
                    <Edge cubics="!999 -104(;999,-104 1000,-78 1000,-78q999 -104 1000 -78);"/>
                    <Edge cubics="!1004 29(;1003,27 1001,25 1000,22q1004 29Q1002 26q1000 22);"/>
                    <Edge cubics="!1000 22(;1000,28 999,33 997,36q1000 22Q1000 31q997 36);"/>
                    <Edge cubics="!978 -50(;979,-55 979,-59 980,-62q978 -50Q979 -58q980 -62);"/>
                    <Edge cubics="!815 538(;816,538 816,538 817,538q815 538Q816 538q817 538);"/>
                    <Edge cubics="!817 538(;821,536 825,535 830,535q817 538Q823 535q830 535);"/>
                    <Edge cubics="!847 547(;847,548 847,549 848,550q847 547Q847 548q848 550);"/>
                    <Edge cubics="!848 550(;848,550 856,546 856,546q848 550 856 546);"/>
                    <Edge cubics="!759 321(;759,322 759,323 758,325q759 321Q759 322q758 325);"/>
                    <Edge cubics="!749 357(;749,357 749,358 749,358q749 357 749 358);"/>
                    <Edge cubics="!750 356(;749,357 749,357 749,357q750 356Q749 357q749 357);"/>
                    <Edge cubics="!760 349(;757,350 754,353 750,356q760 349Q756 351q750 356);"/>
                    <Edge cubics="!741 336(;742,335 743,335 744,334q741 336Q742 335q744 334);"/>
                    <Edge cubics="!686 366(;686,366 689,361 689,361q686 366 689 361);"/>
                    <Edge cubics="!624 423(;624,423 652,417 652,417q624 423 652 417);"/>
                    <Edge cubics="!660 405(;658,406 656,406 654,406q660 405Q657 406q654 406);"/>
                    <Edge cubics="!652 417(;652,417 660,405 660,405q652 417 660 405);"/>
                    <Edge cubics="!612 393(;619,389 633,385 654,381q612 393Q623 387q654 381);"/>
                    <Edge cubics="!654 381(;654,381 650,375 650,375q654 381 650 375);"/>
                    <Edge cubics="!622 545(;627,544 633,543 638,543q622 545Q630 543q638 543);"/>
                    <Edge cubics="!660 365(;660,365 686,366 686,366q660 365 686 366);"/>
                    <Edge cubics="!711 592(;711,592 634,584 634,584q711 592 634 584);"/>
                    <Edge cubics="!634 584(;617,588 596,598 570,613q634 584Q609 590q570 613);"/>
                    <Edge cubics="!570 613(;570,613 566,612 566,612q570 613 566 612);"/>
                    <Edge cubics="!796 598(;793,597 792,594 791,590q796 598Q792 596q791 590);"/>
                    <Edge cubics="!791 590(;791,589 791,587 791,586q791 590Q791 588q791 586);"/>
                    <Edge cubics="!791 586(;789,586 787,586 786,586q791 586Q788 586q786 586);"/>
                    <Edge cubics="!560 616(;552,627 542,641 531,659q560 616Q548 632q531 659);"/>
                    <Edge cubics="!478 655(;485,646 491,638 496,633q478 655Q489 641q496 633);"/>
                    <Edge cubics="!496 633(;498,629 500,626 501,623q496 633Q499 627q501 623);"/>
                    <Edge cubics="!501 623(;501,622 501,622 502,622q501 623Q501 622q502 622);"/>
                    <Edge cubics="!502 622(;507,603 512,590 517,581q502 622Q510 594q517 581);"/>
                    <Edge cubics="!563 562(;561,563 559,565 557,567q563 562Q560 564q557 567);"/>
                    <Edge cubics="!455 802(;453,796 451,790 450,784q455 802Q452 793q450 784);"/>
                    <Edge cubics="!450 784(;449,785 447,787 445,789q450 784Q448 786q445 789);"/>
                    <Edge cubics="!445 789(;445,789 431,804 431,804q445 789 431 804);"/>
                    <Edge cubics="!412 791(;413,788 415,785 417,782q412 791Q414 786q417 782);"/>
                    <Edge cubics="!417 782(;412,788 407,794 402,801q417 782Q409 791q402 801);"/>
                    <Edge cubics="!402 801(;402,801 412,791 412,791q402 801 412 791);"/>
                    <Edge cubics="!494 701(;485,711 477,722 470,733q494 701Q481 716q470 733);"/>
                    <Edge cubics="!470 733(;469,737 469,742 469,747q470 733Q469 739q469 747);"/>
                    <Edge cubics="!469 747(;470,764 470,776 469,783q469 747Q470 773q469 783);"/>
                    <Edge cubics="!451 716(;456,694 465,674 478,655q451 716Q458 683q478 655);"/>
                    <Edge cubics="!395 844(;395,844 395,843 395,843q395 844 395 843);"/>
                    <Edge cubics="!318 964(;318,964 318,965 318,965q318 964 318 965);"/>
                    <Edge cubics="!313 984(;325,985 333,989 338,994q313 984Q331 986q338 994);"/>
                    <Edge cubics="!298 977(;298,978 298,980 298,982q298 977Q298 979q298 982);"/>
                    <Edge cubics="!298 982(;302,983 307,983 313,984q298 982Q304 983q313 984);"/>
                    <Edge cubics="!318 965(;312,971 305,975 298,977q318 965Q309 974q298 977);"/>
                    <Edge cubics="!323 1003(;314,1003 305,1004 294,1005q323 1003Q310 1003q294 1005);"/>
                    <Edge cubics="!272 1006(;242,1007 206,1008 164,1011q272 1006Q227 1007q164 1011);"/>
                    <Edge cubics="!566 612(;566,612 560,616 560,616q566 612 560 616);"/>
                    <Edge cubics="!431 804(;418,835 409,868 405,903q431 804Q411 850q405 903);"/>
                    <Edge cubics="!557 567(;566,562 574,558 580,555q557 567Q571 560q580 555);"/>
                    <Edge cubics="!580 555(;575,558 569,560 563,562q580 555Q572 559q563 562);"/>
                    <Edge cubics="!753 308(;755,311 756,313 757,315q753 308Q756 312q757 315);"/>
                    <Edge cubics="!758 325(;763,320 767,316 768,313q758 325Q766 318q768 313);"/>
                    <Edge cubics="!210 337(;210,337 460,337 460,337q210 337 460 337);"/>
                    <Edge cubics="!460 107(;460,107 460,337 460,337q460 107 460 337);"/>
                    <Edge cubics="!210 107(;210,107 210,337 210,337q210 107 210 337);"/>
                    <Edge cubics="!210 -103(;210,-103 460,-103 460,-103q210 -103 460 -103);"/>
                    <Edge cubics="!460 -103(;460,-103 460,107 460,107q460 -103 460 107);"/>
                    <Edge cubics="!210 -103(;210,-103 210,107 210,107q210 -103 210 107);"/>
                    <Edge cubics="!210 107(;210,107 460,107 460,107q210 107 460 107);"/>
                    <Edge cubics="!770 -103(;770,-103 770,107 770,107q770 -103 770 107);"/>
                    <Edge cubics="!460 -293(;460,-293 460,-198 460,-198q460 -293 460 -198);"/>
                    <Edge cubics="!460 -198(;460,-198 460,-103 460,-103q460 -198 460 -103);"/>
                    <Edge cubics="!210 -353(;210,-353 450,-353 450,-353q210 -353 450 -353);"/>
                    <Edge cubics="!450 -353(;450,-353 770,-353 770,-353q450 -353 770 -353);"/>
                    <Edge cubics="!210 -353(;210,-353 210,-103 210,-103q210 -353 210 -103);"/>
                    <Edge cubics="!460 107(;460,107 770,107 770,107q460 107 770 107);"/>
                    <Edge cubics="!770 -353(;770,-353 770,-103 770,-103q770 -353 770 -103);"/>
                    <Edge cubics="!460 -103(;460,-103 770,-103 770,-103q460 -103 770 -103);"/>
                    <Edge cubics="!210 531(;210,531 368,529 368,529q210 531 368 529);"/>
                    <Edge cubics="!210 531(;210,531 210,757 210,757q210 531 210 757);"/>
                    <Edge cubics="!317 757(;317,757 210,757 210,757q317 757 210 757);"/>
                    <Edge cubics="!210 337(;210,337 210,531 210,531q210 337 210 531);"/>
                    <Edge cubics="!460 337(;460,337 460,467 460,467q460 337 460 467);"/>
                    <Edge cubics="!-740 107(;-740,107 -740,-103 -740,-103q-740 107 -740 -103);"/>
                    <Edge cubics="!-740 -103(;-740,-103 -740,-353 -740,-353q-740 -103 -740 -353);"/>
                    <Edge cubics="!-740 757(;-740,757 -740,547 -740,547q-740 757 -740 547);"/>
                    <Edge cubics="!-740 547(;-740,547 -740,337 -740,337q-740 547 -740 337);"/>
                    <Edge cubics="!-300 107(;-300,107 -300,337 -300,337q-300 107 -300 337);"/>
                    <Edge cubics="!-300 -103(;-300,-103 -300,107 -300,107q-300 -103 -300 107);"/>
                    <Edge cubics="!-60 107(;-60,107 -60,337 -60,337q-60 107 -60 337);"/>
                    <Edge cubics="!-60 -103(;-60,-103 -60,107 -60,107q-60 -103 -60 107);"/>
                    <Edge cubics="!-300 337(;-300,337 -60,337 -60,337q-300 337 -60 337);"/>
                    <Edge cubics="!-300 -353(;-300,-353 -300,-103 -300,-103q-300 -353 -300 -103);"/>
                    <Edge cubics="!-300 -103(;-300,-103 -60,-103 -60,-103q-300 -103 -60 -103);"/>
                    <Edge cubics="!-300 -353(;-300,-353 -60,-353 -60,-353q-300 -353 -60 -353);"/>
                    <Edge cubics="!-300 107(;-300,107 -60,107 -60,107q-300 107 -60 107);"/>
                    <Edge cubics="!-300 540(;-300,540 -300,757 -300,757q-300 540 -300 757);"/>
                    <Edge cubics="!-60 757(;-60,757 -300,757 -300,757q-60 757 -300 757);"/>
                    <Edge cubics="!-300 540(;-300,540 -60,536 -60,536q-300 540 -60 536);"/>
                    <Edge cubics="!-60 536(;-60,536 -60,757 -60,757q-60 536 -60 757);"/>
                    <Edge cubics="!-740 -103(;-740,-103 -520,-103 -520,-103q-740 -103 -520 -103);"/>
                    <Edge cubics="!-520 -103(;-520,-103 -300,-103 -300,-103q-520 -103 -300 -103);"/>
                    <Edge cubics="!-740 107(;-740,107 -520,107 -520,107q-740 107 -520 107);"/>
                    <Edge cubics="!-520 107(;-520,107 -300,107 -300,107q-520 107 -300 107);"/>
                    <Edge cubics="!-740 337(;-740,337 -520,337 -520,337q-740 337 -520 337);"/>
                    <Edge cubics="!-520 337(;-520,337 -300,337 -300,337q-520 337 -300 337);"/>
                    <Edge cubics="!-740 547(;-740,547 -520,544 -520,544q-740 547 -520 544);"/>
                    <Edge cubics="!-520 544(;-520,544 -300,540 -300,540q-520 544 -300 540);"/>
                    <Edge cubics="!-300 757(;-300,757 -520,757 -520,757q-300 757 -520 757);"/>
                    <Edge cubics="!-520 757(;-520,757 -740,757 -740,757q-520 757 -740 757);"/>
                    <Edge cubics="!-300 337(;-300,337 -300,540 -300,540q-300 337 -300 540);"/>
                    <Edge cubics="!-740 -353(;-740,-353 -300,-353 -300,-353q-740 -353 -300 -353);"/>
                    <Edge cubics="!-60 337(;-60,337 -60,536 -60,536q-60 337 -60 536);"/>
                    <Edge cubics="!-60 -103(;-60,-103 210,-103 210,-103q-60 -103 210 -103);"/>
                    <Edge cubics="!-60 107(;-60,107 210,107 210,107q-60 107 210 107);"/>
                    <Edge cubics="!-60 337(;-60,337 210,337 210,337q-60 337 210 337);"/>
                    <Edge cubics="!-60 536(;-60,536 210,531 210,531q-60 536 210 531);"/>
                    <Edge cubics="!210 757(;210,757 -60,757 -60,757q210 757 -60 757);"/>
                    <Edge cubics="!-520 107(;-520,107 -520,337 -520,337q-520 107 -520 337);"/>
                    <Edge cubics="!-520 -103(;-520,-103 -520,107 -520,107q-520 -103 -520 107);"/>
                    <Edge cubics="!-520 544(;-520,544 -520,757 -520,757q-520 544 -520 757);"/>
                    <Edge cubics="!-520 337(;-520,337 -520,544 -520,544q-520 337 -520 544);"/>
                    <Edge cubics="!-1021 -984(;-1021,-1011 -1008,-1024 -981,-1024q-1021 -984Q-1021 -1024q-981 -1024);"/>
                    <Edge cubics="!981 -1024(;1008,-1024 1021,-1011 1021,-984q981 -1024Q1021 -1024q1021 -984);"/>
                    <Edge cubics="!-981 -1024(;-981,-1024 981,-1024 981,-1024q-981 -1024 981 -1024);"/>
                    <Edge cubics="!1021 975(;1021,1002 1008,1015 981,1015q1021 975Q1021 1015q981 1015);"/>
                    <Edge cubics="!-981 1015(;-1008,1015 -1021,1002 -1021,975q-981 1015Q-1021 1015q-1021 975);"/>
                    <Edge cubics="!1021 -560(;1020,-535 1007,-523 981,-523q1021 -560Q1020 -523q981 -523);"/>
                    <Edge cubics="!1021 -560(;1021,-560 1021,975 1021,975q1021 -560 1021 975);"/>
                    <Edge cubics="!-981 -523(;-1007,-523 -1020,-535 -1021,-560q-981 -523Q-1020 -523q-1021 -560);"/>
                    <Edge cubics="!-1021 975(;-1021,975 -1021,-560 -1021,-560q-1021 975 -1021 -560);"/>
                    <Edge cubics="!981 -523(;981,-523 -981,-523 -981,-523q981 -523 -981 -523);"/>
                    <Edge cubics="!-1021 -560(;-1021,-560 -1021,-984 -1021,-984q-1021 -560 -1021 -984);"/>
                    <Edge cubics="!1021 -984(;1021,-984 1021,-560 1021,-560q1021 -984 1021 -560);"/>
                    <Edge cubics="!929 836(;929,849 929,863 926,876q929 836Q929 863q926 876);"/>
                    <Edge cubics="!926 876(;923,887 918,897 911,905q926 876Q921 893q911 905);"/>
                    <Edge cubics="!911 905(;890,930 856,940 824,946q911 905Q886 934q824 946);"/>
                    <Edge cubics="!824 946(;801,951 779,955 756,956q824 946Q784 955q756 956);"/>
                    <Edge cubics="!642 929(;641,929 641,929 640,929q642 929 640 929);"/>
                    <Edge cubics="!640 929(;638,929 637,930 637,932q640 929Q637 929q637 932);"/>
                    <Edge cubics="!637 932(;648,932 660,932 671,932q637 932 671 932);"/>
                    <Edge cubics="!671 932(;662,931 652,930 642,929q671 932 642 929);"/>
                    <Edge cubics="!733 727(;743,716 751,705 759,693q733 727Q746 713q759 693);"/>
                    <Edge cubics="!891 461(;893,444 892,426 900,410q891 461Q892 444q893 435Q895 420q900 410);"/>
                    <Edge cubics="!900 410(;907,394 927,382 942,390q900 410Q906 397q918 391Q931 384q942 390);"/>
                    <Edge cubics="!942 390(;952,395 957,406 957,417q942 390Q957 398q957 417);"/>
                    <Edge cubics="!957 417(;958,428 956,438 954,449q957 417Q958 427q954 449);"/>
                    <Edge cubics="!944 501(;940,520 933,538 925,552q944 501 925 552);"/>
                    <Edge cubics="!530 961(;492,975 452,986 411,987q530 961Q463 986q411 987);"/>
                    <Edge cubics="!411 987(;400,988 387,987 377,982q411 987Q391 989q377 982);"/>
                    <Edge cubics="!377 982(;367,976 358,965 359,954q377 982Q358 970q359 954);"/>
                    <Edge cubics="!359 954(;360,942 371,933 382,929q359 954Q360 937q382 929);"/>
                    <Edge cubics="!382 929(;393,925 405,924 416,923q382 929Q393 925q416 923);"/>
                    <Edge cubics="!416 923(;446,920 474,911 502,901q416 923Q450 920q502 901);"/>
                    <Edge cubics="!502 901(;522,894 542,886 560,875q502 901Q538 888q560 875);"/>
                    <Edge cubics="!560 875(;580,864 597,849 614,834q560 875Q580 864q614 834);"/>
                    <Edge cubics="!614 834(;636,815 658,796 681,777q614 834 681 777);"/>
                    <Edge cubics="!681 777(;699,761 717,746 733,727q681 777Q720 742q733 727);"/>
                    <Edge cubics="!883 637(;899,639 908,658 905,673q883 637Q895 638q901 650Q907 661q905 673);"/>
                    <Edge cubics="!905 673(;903,689 892,702 882,715q905 673Q903 687q882 715);"/>
                    <Edge cubics="!882 715(;861,739 841,763 821,787q882 715 821 787);"/>
                    <Edge cubics="!821 787(;794,819 766,851 730,873q821 787Q768 850q730 873);"/>
                    <Edge cubics="!730 873(;718,880 705,886 691,886q730 873Q708 886q691 886);"/>
                    <Edge cubics="!269 903(;286,880 293,851 300,823q269 903Q286 881q300 823);"/>
                    <Edge cubics="!317 754(;325,718 334,682 339,646q317 754Q336 670q339 646);"/>
                    <Edge cubics="!648 428(;681,414 713,398 739,375q648 428Q708 403q739 375);"/>
                    <Edge cubics="!275 983(;263,985 249,981 242,970q275 983Q253 987q242 970);"/>
                    <Edge cubics="!245 934(;251,922 261,914 269,903q245 934Q249 927q256 918Q267 906q269 903);"/>
                    <Edge cubics="!920 147(;938,148 947,169 949,187q920 147Q945 148q949 187);"/>
                    <Edge cubics="!949 187(;950,207 948,227 944,247q949 187Q950 215q944 247);"/>
                    <Edge cubics="!944 247(;937,285 927,322 914,359q944 247Q934 303q914 359);"/>
                    <Edge cubics="!914 359(;899,397 881,434 852,463q914 359Q887 428q852 463);"/>
                    <Edge cubics="!704 531(;696,536 685,537 675,537q704 531Q694 537q675 537);"/>
                    <Edge cubics="!545 542(;519,547 498,566 479,584q545 542Q518 547q479 584);"/>
                    <Edge cubics="!479 584(;468,594 457,605 452,619q479 584Q458 604q452 619);"/>
                    <Edge cubics="!452 619(;449,627 448,637 445,645q452 619 445 645);"/>
                    <Edge cubics="!445 645(;442,653 436,660 433,667q445 645Q442 653q433 667);"/>
                    <Edge cubics="!433 667(;429,676 427,685 426,694q433 667Q428 679q426 694);"/>
                    <Edge cubics="!426 694(;423,709 420,723 417,738q426 694 417 738);"/>
                    <Edge cubics="!405 778(;400,792 394,804 388,817q405 778Q402 788q388 817);"/>
                    <Edge cubics="!837 489(;836,498 830,507 823,513q837 489Q836 502q823 513);"/>
                    <Edge cubics="!823 513(;816,519 807,522 798,525q823 513Q816 519q798 525);"/>
                    <Edge cubics="!889 173(;898,155 909,146 920,147q889 173Q903 146q920 147);"/>
                    <Edge cubics="!770 342(;780,330 791,316 802,300q770 342Q785 324q802 300);"/>
                    <Edge cubics="!770 337(;770,337 770,342 770,342q770 337 770 342);"/>
                    <Edge cubics="!836 478(;837,481 838,485 837,489q836 478Q838 483q837 489);"/>
                    <Edge cubics="!852 463(;847,468 841,473 836,478q852 463Q844 471q836 478);"/>
                    <Edge cubics="!672 880(;669,878 667,876 665,873q672 880Q668 877q665 873);"/>
                    <Edge cubics="!874 637(;874,637 873,638 873,638q874 637 873 638);"/>
                    <Edge cubics="!873 638(;876,637 880,636 883,637q873 638Q878 636q883 637);"/>
                    <Edge cubics="!759 693(;759,693 821,606 821,606q759 693 821 606);"/>
                    <Edge cubics="!456 468(;457,468 458,468 460,467q456 468Q457 468q460 467);"/>
                    <Edge cubics="!393 496(;408,483 429,473 456,468q393 496Q416 476q456 468);"/>
                    <Edge cubics="!368 529(;375,516 383,505 393,496q368 529Q378 509q393 496);"/>
                    <Edge cubics="!353 564(;357,551 362,539 368,529q353 564Q359 544q368 529);"/>
                    <Edge cubics="!317 757(;317,757 317,754 317,754q317 757 317 754);"/>
                    <Edge cubics="!300 823(;300,823 317,757 317,757q300 823 317 757);"/>
                    <Edge cubics="!339 646(;346,602 350,575 353,564q339 646Q349 580q353 564);"/>
                    <Edge cubics="!316 964(;313,965 309,965 306,965q316 964Q311 965q306 965);"/>
                    <Edge cubics="!306 965(;295,975 285,981 275,983q306 965Q290 980q275 983);"/>
                    <Edge cubics="!631 903(;630,904 629,905 628,906q631 903Q629 904q628 906);"/>
                    <Edge cubics="!653 884(;645,891 638,898 631,903q653 884Q641 895q631 903);"/>
                    <Edge cubics="!653 884(;656,883 661,883 666,883q653 884Q658 883q666 883);"/>
                    <Edge cubics="!550 953(;543,956 537,958 530,961q550 953Q540 957q530 961);"/>
                    <Edge cubics="!599 927(;584,937 567,946 550,953q599 927Q576 942q550 953);"/>
                    <Edge cubics="!628 906(;617,915 608,922 599,927q628 906Q612 919q599 927);"/>
                    <Edge cubics="!756 956(;756,956 550,953 550,953q756 956 550 953);"/>
                    <Edge cubics="!460 467(;469,466 492,463 528,458q460 467Q474 465q528 458);"/>
                    <Edge cubics="!665 873(;661,877 657,881 653,884q665 873Q659 879q653 884);"/>
                    <Edge cubics="!691 886(;683,885 677,883 672,880q691 886Q679 885q672 880);"/>
                    <Edge cubics="!666 883(;668,882 670,881 672,880q666 883Q669 882q672 880);"/>
                    <Edge cubics="!925 552(;928,556 930,563 930,574q925 552Q930 558q930 574);"/>
                    <Edge cubics="!616 439(;615,439 615,439 614,439q616 439Q615 439q614 439);"/>
                    <Edge cubics="!627 539(;625,541 623,543 622,545q627 539Q624 542q622 545);"/>
                    <Edge cubics="!556 542(;556,542 545,542 545,542q556 542 545 542);"/>
                    <Edge cubics="!627 539(;627,539 556,542 556,542q627 539 556 542);"/>
                    <Edge cubics="!517 581(;523,570 536,557 556,542q517 581Q526 564q556 542);"/>
                    <Edge cubics="!528 458(;559,454 588,448 616,439q528 458Q574 452q616 439);"/>
                    <Edge cubics="!616 439(;627,436 637,432 648,428q616 439Q632 434q648 428);"/>
                    <Edge cubics="!222 955(;222,955 239,956 239,956q222 955 239 956);"/>
                    <Edge cubics="!242 970(;239,965 238,961 239,956q242 970Q238 963q239 956);"/>
                    <Edge cubics="!239 956(;239,949 241,942 245,934q239 956Q239 946q245 934);"/>
                    <Edge cubics="!414 750(;411,760 408,769 405,778q414 750Q410 765q405 778);"/>
                    <Edge cubics="!417 738(;416,742 415,746 414,750q417 738Q416 744q414 750);"/>
                    <Edge cubics="!414 750(;421,742 427,735 433,729q414 750Q424 738q433 729);"/>
                    <Edge cubics="!361 881(;355,895 350,910 345,925q361 881Q352 902q345 925);"/>
                    <Edge cubics="!388 817(;378,837 369,858 361,881q388 817Q373 847q361 881);"/>
                    <Edge cubics="!395 843(;386,854 374,867 361,881q395 843Q381 860q361 881);"/>
                    <Edge cubics="!342 935(;347,936 353,939 359,944q342 935Q350 937q359 944);"/>
                    <Edge cubics="!321 963(;319,963 317,963 316,964q321 963Q318 963q316 964);"/>
                    <Edge cubics="!325 960(;324,960 324,960 324,961q325 960Q324 960q324 961);"/>
                    <Edge cubics="!324 961(;323,961 322,962 321,963q324 961Q322 961q321 963);"/>
                    <Edge cubics="!321 963(;320,963 319,963 318,964q321 963Q319 963q318 964);"/>
                    <Edge cubics="!288 1015(;288,1015 271,1015 271,1015q288 1015 271 1015);"/>
                    <Edge cubics="!288 1015(;285,1019 280,1022 275,1024q288 1015Q283 1021q275 1024);"/>
                    <Edge cubics="!294 1005(;293,1009 291,1012 288,1015q294 1005Q292 1011q288 1015);"/>
                    <Edge cubics="!271 1015(;271,1012 271,1009 272,1006q271 1015Q271 1011q272 1006);"/>
                    <Edge cubics="!275 1024(;272,1022 271,1019 271,1015q275 1024Q271 1021q271 1015);"/>
                    <Edge cubics="!345 925(;344,928 343,932 342,935q345 925Q343 930q342 935);"/>
                    <Edge cubics="!859 211(;860,209 862,207 863,205q859 211Q861 208q863 205);"/>
                    <Edge cubics="!846 237(;851,228 856,219 859,211q846 237Q854 223q859 211);"/>
                    <Edge cubics="!846 237(;845,238 844,238 843,239q846 237Q844 238q843 239);"/>
                    <Edge cubics="!802 300(;804,297 806,295 808,293q802 300Q805 296q808 293);"/>
                    <Edge cubics="!799 288(;802,287 805,289 808,293q799 288Q804 287q808 293);"/>
                    <Edge cubics="!808 293(;823,272 836,253 846,237q808 293Q831 261q846 237);"/>
                    <Edge cubics="!770 292(;770,292 770,308 770,308q770 292 770 308);"/>
                    <Edge cubics="!770 292(;765,297 759,303 753,308q770 292Q762 300q753 308);"/>
                    <Edge cubics="!768 313(;769,311 769,309 770,308q768 313Q769 310q770 308);"/>
                    <Edge cubics="!743 287(;752,276 761,267 770,259q743 287Q756 271q770 259);"/>
                    <Edge cubics="!770 259(;770,259 770,292 770,292q770 259 770 292);"/>
                    <Edge cubics="!729 337(;729,337 734,337 734,337q729 337 734 337);"/>
                    <Edge cubics="!729 337(;728,338 727,339 726,340q729 337Q727 339q726 340);"/>
                    <Edge cubics="!733 330(;732,333 730,335 729,337q733 330Q731 334q729 337);"/>
                    <Edge cubics="!734 337(;736,336 738,336 741,336q734 337Q737 336q741 336);"/>
                    <Edge cubics="!726 340(;729,339 731,338 734,337q726 340Q730 338q734 337);"/>
                    <Edge cubics="!747 368(;753,362 759,355 766,347q747 368Q756 359q766 347);"/>
                    <Edge cubics="!766 347(;763,348 761,348 760,349q766 347Q762 348q760 349);"/>
                    <Edge cubics="!749 358(;749,361 748,365 747,368q749 358Q749 363q747 368);"/>
                    <Edge cubics="!734 337(;734,337 770,337 770,337q734 337 770 337);"/>
                    <Edge cubics="!766 347(;767,345 769,343 770,342q766 347Q768 344q770 342);"/>
                    <Edge cubics="!739 375(;742,373 744,371 747,368q739 375Q743 372q747 368);"/>
                    <Edge cubics="!689 361(;695,352 701,344 706,337q689 361Q698 348q706 337);"/>
                    <Edge cubics="!706 337(;706,337 729,337 729,337q706 337 729 337);"/>
                    <Edge cubics="!706 337(;712,328 718,319 723,312q706 337Q715 323q723 312);"/>
                    <Edge cubics="!770 308(;770,308 770,337 770,337q770 308 770 337);"/>
                    <Edge cubics="!770 308(;772,302 774,298 775,297q770 308Q773 299q775 297);"/>
                    <Edge cubics="!770 259(;779,250 789,243 799,237q770 259Q784 246q799 237);"/>
                    <Edge cubics="!779 284(;776,287 773,289 770,292q779 284Q775 288q770 292);"/>
                    <Edge cubics="!856 546(;858,545 860,545 862,544q856 546Q859 545q862 544);"/>
                    <Edge cubics="!862 544(;863,541 864,539 865,537q862 544Q863 540q865 537);"/>
                    <Edge cubics="!753 536(;748,537 744,537 740,537q753 536Q746 537q740 537);"/>
                    <Edge cubics="!725 537(;716,536 709,534 704,531q725 537Q712 536q704 531);"/>
                    <Edge cubics="!740 537(;735,537 730,537 725,537q740 537Q732 537q725 537);"/>
                    <Edge cubics="!821 606(;822,604 824,602 825,601q821 606Q823 603q825 601);"/>
                    <Edge cubics="!825 601(;818,600 810,600 803,599q825 601Q814 600q803 599);"/>
                    <Edge cubics="!798 525(;784,530 769,534 753,536q798 525Q777 533q753 536);"/>
                    <Edge cubics="!753 536(;776,535 797,536 815,538q753 536Q788 535q815 538);"/>
                    <Edge cubics="!825 601(;842,576 854,557 862,544q825 601Q850 564q862 544);"/>
                    <Edge cubics="!945 496(;945,496 944,501 944,501q945 496 944 501);"/>
                    <Edge cubics="!954 449(;954,449 945,496 945,496q954 449 945 496);"/>
                    <Edge cubics="!940 596(;937,597 933,597 930,597q940 596Q935 597q930 597);"/>
                    <Edge cubics="!930 574(;930,574 930,597 930,597q930 574 930 597);"/>
                    <Edge cubics="!898 600(;891,612 883,624 874,637q898 600Q887 618q874 637);"/>
                    <Edge cubics="!925 552(;918,567 909,583 898,600q925 552Q914 574q898 600);"/>
                    <Edge cubics="!865 537(;879,510 888,485 891,461q865 537Q886 497q891 461);"/>
                    <Edge cubics="!930 597(;930,597 929,836 929,836q930 597 929 836);"/>
                    <Edge cubics="!981 1015(;981,1015 288,1015 288,1015q981 1015 288 1015);"/>
                    <Edge cubics="!675 537(;675,537 627,539 627,539q675 537 627 539);"/>
                    <Edge cubics="!460 337(;460,337 706,337 706,337q460 337 706 337);"/>
                    <Edge cubics="!770 107(;770,107 770,259 770,259q770 107 770 259);"/>
                    <Edge cubics="!863 205(;872,188 880,178 889,173q863 205Q876 180q889 173);"/>
                    <Edge cubics="!878 170(;878,170 863,205 863,205q878 170 863 205);"/>
                    <Edge cubics="!638 543(;670,540 699,538 725,537q638 543Q686 538q725 537);"/>
                    <Edge cubics="!271 1015(;271,1015 -981,1015 -981,1015q271 1015 -981 1015);"/>
                    <Edge cubics="!-437 -410(;-437,-421 -438,-432 -439,-443p-437 -410 -439 -443);"/>
                    <Edge cubics="!-449 -396(;-448,-402 -443,-408 -437,-410q-449 -396Q-447 -407q-437 -410);"/>
                    <Edge cubics="!-272 -474(;-269,-469 -272,-464 -276,-461q-272 -474Q-268 -467q-276 -461);"/>
                    <Edge cubics="!-276 -461(;-280,-459 -285,-459 -290,-459q-276 -461Q-280 -459q-290 -459);"/>
                    <Edge cubics="!-392 -460(;-414,-460 -439,-462 -451,-480q-392 -460Q-438 -460q-451 -480);"/>
                    <Edge cubics="!-249 -370(;-252,-369 -256,-369 -260,-369q-249 -370 -260 -369);"/>
                    <Edge cubics="!-379 -511(;-369,-513 -358,-515 -349,-509q-379 -511Q-358 -515q-349 -509);"/>
                    <Edge cubics="!-349 -509(;-346,-507 -344,-504 -341,-503q-349 -509 -341 -503);"/>
                    <Edge cubics="!-341 -503(;-337,-500 -331,-499 -326,-499q-341 -503Q-336 -499q-326 -499);"/>
                    <Edge cubics="!-326 -499(;-320,-499 -314,-498 -308,-498q-326 -499 -308 -498);"/>
                    <Edge cubics="!-346 -360(;-350,-358 -355,-358 -360,-358q-346 -360Q-350 -358q-360 -358);"/>
                    <Edge cubics="!-360 -358(;-366,-359 -372,-359 -377,-363q-360 -358Q-374 -360q-377 -363);"/>
                    <Edge cubics="!-344 -332(;-339,-330 -334,-327 -334,-322q-344 -332Q-334 -328q-334 -322);"/>
                    <Edge cubics="!-390 -272(;-397,-272 -404,-271 -410,-274q-390 -272Q-406 -272q-410 -274);"/>
                    <Edge cubics="!-410 -274(;-416,-276 -421,-284 -419,-290q-410 -274Q-415 -276q-417 -280Q-420 -286q-419 -290);"/>
                    <Edge cubics="!-419 -290(;-418,-294 -414,-297 -410,-299q-419 -290Q-418 -295q-410 -299);"/>
                    <Edge cubics="!-375 -116(;-386,-120 -394,-130 -396,-141q-375 -116Q-393 -122q-396 -141);"/>
                    <Edge cubics="!-396 -141(;-397,-147 -397,-153 -396,-160q-396 -141Q-397 -150q-396 -160);"/>
                    <Edge cubics="!-396 -160(;-396,-168 -395,-177 -395,-185q-396 -160 -395 -185);"/>
                    <Edge cubics="!-395 -185(;-394,-196 -393,-208 -389,-218q-395 -185Q-393 -208q-389 -218);"/>
                    <Edge cubics="!-413 -316(;-415,-330 -399,-339 -385,-341q-413 -316Q-414 -326q-405 -333Q-397 -339q-385 -341);"/>
                    <Edge cubics="!-385 -341(;-376,-343 -366,-343 -358,-339q-385 -341Q-369 -345q-358 -339);"/>
                    <Edge cubics="!-337 -297(;-331,-255 -333,-213 -342,-171q-337 -297Q-328 -235q-342 -171);"/>
                    <Edge cubics="!-342 -171(;-330,-167 -329,-150 -333,-138q-342 -171Q-334 -168q-331 -157Q-330 -148q-333 -138);"/>
                    <Edge cubics="!-333 -138(;-336,-130 -341,-122 -348,-118q-333 -138Q-338 -123q-348 -118);"/>
                    <Edge cubics="!-348 -118(;-356,-113 -366,-112 -375,-116q-348 -118Q-361 -110q-375 -116);"/>
                    <Edge cubics="!-385 -25(;-385,-34 -388,-42 -389,-51q-385 -25Q-388 -42q-389 -51);"/>
                    <Edge cubics="!-389 -94(;-381,-92 -372,-94 -364,-94q-389 -94Q-389 -94q-364 -94);"/>
                    <Edge cubics="!-364 -94(;-355,-94 -346,-92 -340,-86q-364 -94Q-348 -94q-340 -86);"/>
                    <Edge cubics="!-340 -86(;-336,-82 -334,-75 -336,-69q-340 -86Q-333 -79q-336 -69);"/>
                    <Edge cubics="!-336 -69(;-337,-64 -341,-58 -346,-56q-336 -69Q-338 -59q-346 -56);"/>
                    <Edge cubics="!-399 -57(;-406,-60 -410,-69 -408,-76q-399 -57Q-412 -62q-408 -76);"/>
                    <Edge cubics="!-408 -76(;-407,-84 -401,-90 -393,-92q-408 -76Q-406 -89q-393 -92);"/>
                    <Edge cubics="!-393 -92(;-392,-92 -390,-92 -389,-94q-393 -92Q-390 -92q-389 -94);"/>
                    <Edge cubics="!-773 102(;-768,111 -771,123 -768,134q-773 102Q-768 111q-768 134);"/>
                    <Edge cubics="!-768 134(;-759,128 -746,135 -742,145q-768 134Q-761 130q-753 134Q-745 137q-742 145);"/>
                    <Edge cubics="!-743 177(;-746,186 -749,195 -753,203q-743 177 -753 203);"/>
                    <Edge cubics="!-753 203(;-757,211 -762,218 -769,223q-753 203Q-760 216q-769 223);"/>
                    <Edge cubics="!-999 125(;-995,117 -991,110 -986,103p-999 125 -986 103);"/>
                    <Edge cubics="!-986 103(;-982,97 -977,92 -970,89q-986 103Q-979 93q-970 89);"/>
                    <Edge cubics="!-970 89(;-959,85 -946,91 -935,97q-970 89Q-958 85q-935 97);"/>
                    <Edge cubics="!-935 97(;-932,99 -928,101 -924,102q-935 97 -924 102);"/>
                    <Edge cubics="!-924 102(;-918,103 -913,101 -907,102q-924 102Q-918 103q-907 102);"/>
                    <Edge cubics="!-907 102(;-899,104 -892,110 -890,119q-907 102Q-893 106q-890 119);"/>
                    <Edge cubics="!-890 119(;-890,111 -885,103 -877,99q-890 119Q-890 106q-877 99);"/>
                    <Edge cubics="!-877 99(;-870,96 -861,97 -855,102q-877 99Q-865 94q-855 102);"/>
                    <Edge cubics="!-855 102(;-855,75 -855,48 -854,21q-855 102 -854 21);"/>
                    <Edge cubics="!-854 21(;-854,14 -854,6 -849,0q-854 21Q-854 6q-849 0);"/>
                    <Edge cubics="!-849 0(;-845,-5 -839,-7 -832,-8q-849 0Q-844 -6q-832 -8);"/>
                    <Edge cubics="!-832 -8(;-825,-9 -816,-7 -811,-2q-832 -8Q-819 -10q-811 -2);"/>
                    <Edge cubics="!-811 -2(;-802,8 -806,24 -800,36q-811 -2Q-806 4q-804 16Q-802 31q-800 36);"/>
                    <Edge cubics="!-800 36(;-798,41 -793,46 -791,51q-800 36 -791 51);"/>
                    <Edge cubics="!-791 51(;-789,58 -790,65 -789,72q-791 51Q-789 58q-789 72);"/>
                    <Edge cubics="!-789 72(;-787,78 -783,83 -781,89q-789 72 -781 89);"/>
                    <Edge cubics="!-789 256(;-789,264 -790,273 -795,279q-789 256Q-789 272q-795 279);"/>
                    <Edge cubics="!-795 279(;-799,285 -807,287 -813,286q-795 279Q-801 288q-813 286);"/>
                    <Edge cubics="!-813 286(;-820,285 -826,279 -828,273q-813 286Q-824 284q-828 273);"/>
                    <Edge cubics="!-828 273(;-830,283 -833,294 -838,303q-828 273Q-832 292q-838 303);"/>
                    <Edge cubics="!-838 303(;-843,313 -851,323 -861,322q-838 303Q-848 323q-861 322);"/>
                    <Edge cubics="!-861 322(;-868,321 -874,315 -877,308q-861 322Q-872 321q-877 308);"/>
                    <Edge cubics="!-877 308(;-879,302 -880,294 -880,287q-877 308Q-880 299q-880 287);"/>
                    <Edge cubics="!-880 287(;-880,259 -880,231 -880,203q-880 287 -880 203);"/>
                    <Edge cubics="!-880 203(;-885,209 -888,217 -890,225q-880 203Q-886 211q-890 225);"/>
                    <Edge cubics="!-890 225(;-901,254 -911,284 -922,314q-890 225 -922 314);"/>
                    <Edge cubics="!-922 314(;-926,327 -931,340 -934,354q-922 314Q-933 351q-934 354);"/>
                    <Edge cubics="!-934 354(;-935,362 -936,370 -940,377q-934 354Q-936 370q-940 377);"/>
                    <Edge cubics="!-940 377(;-943,385 -950,391 -958,391q-940 377Q-945 391q-958 391);"/>
                    <Edge cubics="!-958 391(;-966,392 -973,386 -976,380q-958 391Q-970 393q-976 380);"/>
                    <Edge cubics="!-976 380(;-980,373 -980,365 -980,358q-976 380Q-980 373q-980 358);"/>
                    <Edge cubics="!-980 358(;-978,341 -970,327 -966,311q-980 358Q-979 348q-974 334Q-967 316q-966 311);"/>
                    <Edge cubics="!-966 311(;-963,295 -964,278 -965,262q-966 311Q-963 295q-965 262);"/>
                    <Edge cubics="!-965 262(;-967,262 -968,263 -970,264q-965 262 -970 264);"/>
                    <Edge cubics="!-970 264(;-968,271 -970,280 -976,285q-970 264Q-966 277q-976 285);"/>
                    <Edge cubics="!-976 285(;-982,291 -991,292 -998,289q-976 285Q-985 294q-998 289);"/>
                    <Edge cubics="!-998 289(;-1006,286 -1011,278 -1013,270q-998 289Q-1009 285q-1013 270);"/>
                    <Edge cubics="!-1013 270(;-1015,262 -1015,253 -1016,245q-1013 270Q-1015 253q-1016 245);"/>
                    <Edge cubics="!-1016 245(;-1017,235 -1018,226 -1019,216q-1016 245 -1019 216);"/>
                    <Edge cubics="!-1019 216(;-1020,194 -1014,173 -1008,151q-1019 216Q-1020 195q-1008 151);"/>
                    <Edge cubics="!-1008 151(;-1005,142 -1002,133 -999,125q-1008 151 -999 125);"/>
                    <Edge cubics="!-717 241(;-725,233 -724,220 -725,209q-717 241Q-723 235q-725 209);"/>
                    <Edge cubics="!-725 209(;-725,190 -732,171 -730,152q-725 209Q-725 201q-728 181Q-731 162q-730 152);"/>
                    <Edge cubics="!-730 152(;-729,146 -728,140 -724,135q-730 152Q-728 140q-724 135);"/>
                    <Edge cubics="!-724 135(;-721,130 -715,128 -709,127q-724 135Q-720 129q-709 127);"/>
                    <Edge cubics="!-685 220(;-685,226 -685,232 -688,237q-685 220Q-685 232q-688 237);"/>
                    <Edge cubics="!-688 237(;-694,247 -709,249 -717,241q-688 237Q-692 245q-702 246Q-711 247q-717 241);"/>
                    <Edge cubics="!-686 122(;-680,118 -673,117 -666,117q-686 122Q-678 117q-666 117);"/>
                    <Edge cubics="!-525 147(;-525,155 -532,161 -538,166q-525 147Q-525 155q-538 166);"/>
                    <Edge cubics="!-538 166(;-545,172 -553,178 -562,182q-538 166Q-551 177q-562 182);"/>
                    <Edge cubics="!-562 182(;-573,187 -587,187 -600,187q-562 182Q-573 187q-600 187);"/>
                    <Edge cubics="!-550 112(;-542,112 -534,118 -531,125q-550 112Q-537 112q-531 125);"/>
                    <Edge cubics="!-562 117(;-559,114 -554,113 -550,114q-562 117Q-557 112q-550 114);"/>
                    <Edge cubics="!-550 114(;-550,113 -550,113 -550,112q-550 114 -550 112);"/>
                    <Edge cubics="!711 -359(;701,-358 690,-357 680,-361q711 -359Q690 -357q680 -361);"/>
                    <Edge cubics="!729 -145(;732,-131 725,-116 712,-111q729 -145Q731 -134q727 -125Q722 -115q712 -111);"/>
                    <Edge cubics="!712 -111(;700,-105 683,-111 678,-124q712 -111Q703 -106q692 -110Q682 -114q678 -124);"/>
                    <Edge cubics="!683 -329(;687,-339 699,-346 708,-342q683 -329Q686 -337q694 -341Q701 -345q708 -342);"/>
                    <Edge cubics="!708 -342(;718,-337 720,-324 720,-313q708 -342Q720 -336q720 -313);"/>
                    <Edge cubics="!720 -313(;721,-279 722,-244 719,-209q720 -313Q722 -244q719 -209);"/>
                    <Edge cubics="!719 -169(;722,-160 727,-153 729,-145q719 -169Q722 -160q729 -145);"/>
                    <Edge cubics="!-34 -494(;-18,-494 -2,-494 13,-489q-34 -494Q-2 -494q13 -489);"/>
                    <Edge cubics="!-146 -501(;-109,-497 -72,-494 -34,-494q-146 -501Q-81 -494q-34 -494);"/>
                    <Edge cubics="!839 -485(;859,-472 871,-448 870,-425q839 -485Q872 -464q870 -425);"/>
                    <Edge cubics="!870 -425(;869,-401 855,-379 834,-368q870 -425Q868 -386q834 -368);"/>
                    <Edge cubics="!834 -368(;812,-356 784,-357 759,-359q834 -368Q810 -355q759 -359);"/>
                    <Edge cubics="!29 -496(;47,-507 70,-508 92,-509q29 -496Q47 -507q92 -509);"/>
                    <Edge cubics="!774 -501(;797,-499 820,-497 839,-485q774 -501Q820 -497q839 -485);"/>
                    <Edge cubics="!409 75(;392,83 373,83 354,85q409 75Q398 80q354 85);"/>
                    <Edge cubics="!641 -80(;661,-94 686,-96 708,-87q641 -80Q672 -102q708 -87);"/>
                    <Edge cubics="!708 -87(;729,-78 745,-58 749,-35q708 -87Q743 -72q749 -35);"/>
                    <Edge cubics="!749 -35(;751,-26 751,-17 750,-8q749 -35Q752 -23q750 -8);"/>
                    <Edge cubics="!750 -8(;748,0 747,8 743,16q750 -8Q745 12q743 16);"/>
                    <Edge cubics="!743 16(;740,24 734,31 728,37q743 16Q739 26q728 37);"/>
                    <Edge cubics="!728 37(;719,45 708,51 698,56q728 37Q718 46q698 56);"/>
                    <Edge cubics="!672 68(;661,71 651,72 640,73q672 68Q661 71q640 73);"/>
                    <Edge cubics="!640 73(;613,76 585,77 558,77q640 73Q604 77q558 77);"/>
                    <Edge cubics="!-30 -82(;-17,-83 -3,-84 11,-85p-30 -82 11 -85);"/>
                    <Edge cubics="!11 -85(;13,-85 16,-87 15,-88q11 -85Q18 -85q15 -88);"/>
                    <Edge cubics="!15 -88(;37,-89 60,-87 82,-84q15 -88Q43 -89q82 -84);"/>
                    <Edge cubics="!-46 -49(;-43,-48 -40,-51 -40,-54q-46 -49Q-40 -47q-40 -54);"/>
                    <Edge cubics="!-40 -54(;-37,-54 -34,-55 -30,-55q-40 -54 -30 -55);"/>
                    <Edge cubics="!-30 -55(;-30,-64 -30,-73 -30,-82q-30 -55 -30 -82);"/>
                    <Edge cubics="!436 -317(;438,-317 441,-317 442,-315q436 -317Q441 -317q442 -315);"/>
                    <Edge cubics="!442 -315(;446,-313 448,-306 453,-307q442 -315Q443 -314q447 -310Q450 -306q453 -307);"/>
                    <Edge cubics="!453 -307(;452,-251 452,-195 452,-139q453 -307 452 -139);"/>
                    <Edge cubics="!452 -139(;445,-131 438,-123 428,-120q452 -139Q438 -123q428 -120);"/>
                    <Edge cubics="!428 -120(;424,-118 419,-118 415,-117q428 -120Q419 -118q415 -117);"/>
                    <Edge cubics="!415 -117(;357,-112 298,-113 240,-120q415 -117Q327 -109q240 -120);"/>
                    <Edge cubics="!565 -333(;596,-333 628,-332 659,-332q565 -333 659 -332);"/>
                    <Edge cubics="!659 -332(;665,-332 670,-332 676,-331q659 -332Q670 -332q676 -331);"/>
                    <Edge cubics="!485 -125(;485,-137 485,-149 485,-161q485 -125 485 -161);"/>
                    <Edge cubics="!485 -161(;481,-162 478,-164 475,-165q485 -161 475 -165);"/>
                    <Edge cubics="!-291 -48(;-216,-48 -142,-47 -68,-47p-291 -48 -68 -47);"/>
                    <Edge cubics="!-68 -47(;-68,0 -67,45 -67,92p-68 -47 -67 92);"/>
                    <Edge cubics="!-50 100(;-50,54 -50,8 -50,-39p-50 100 -50 -39);"/>
                    <Edge cubics="!22 96(;18,101 11,102 4,102q22 96Q17 102q4 102);"/>
                    <Edge cubics="!4 102(;-14,101 -32,101 -50,100q4 102 -50 100);"/>
                    <Edge cubics="!-142 96(;-190,96 -238,96 -285,96q-142 96 -285 96);"/>
                    <Edge cubics="!-317 118(;-317,164 -317,211 -318,257p-317 118 -318 257);"/>
                    <Edge cubics="!-318 257(;-380,256 -443,253 -505,250q-318 257Q-381 256q-505 250);"/>
                    <Edge cubics="!-505 250(;-505,204 -505,158 -505,112q-505 250 -505 112);"/>
                    <Edge cubics="!-505 112(;-443,111 -380,113 -317,118q-505 112Q-412 111q-317 118);"/>
                    <Edge cubics="!-384 98(;-385,96 -386,93 -386,90p-384 98 -386 90);"/>
                    <Edge cubics="!-308 -36(;-308,10 -308,55 -308,101q-308 -36 -308 101);"/>
                    <Edge cubics="!-308 101(;-330,101 -352,101 -375,101q-308 101 -375 101);"/>
                    <Edge cubics="!-375 101(;-378,101 -381,100 -384,98q-375 101Q-379 101q-384 98);"/>
                    <Edge cubics="!202 -66(;203,-20 203,26 203,72q202 -66 203 72);"/>
                    <Edge cubics="!282 87(;261,86 241,86 219,86q282 87 219 86);"/>
                    <Edge cubics="!219 86(;219,39 220,-7 220,-53q219 86 220 -53);"/>
                    <Edge cubics="!522 96(;505,96 487,96 470,95p522 96 470 95);"/>
                    <Edge cubics="!470 95(;469,48 469,1 469,-47p470 95 469 -47);"/>
                    <Edge cubics="!469 -47(;469,-54 470,-63 475,-68q469 -47Q469 -62q475 -68);"/>
                    <Edge cubics="!404 -78(;422,-78 440,-77 458,-76p404 -78 458 -76);"/>
                    <Edge cubics="!458 -76(;458,-29 457,18 458,66q458 -76Q458 66q458 66);"/>
                    <Edge cubics="!668 -113(;632,-105 595,-110 560,-115q668 -113Q631 -105q560 -115);"/>
                    <Edge cubics="!230 -174(;230,-178 228,-182 227,-185q230 -174Q230 -176q227 -185);"/>
                    <Edge cubics="!227 -185(;224,-192 224,-199 224,-205q227 -185Q224 -192q224 -205);"/>
                    <Edge cubics="!224 -205(;224,-250 224,-294 225,-338q224 -205 225 -338);"/>
                    <Edge cubics="!225 -338(;242,-338 260,-337 277,-336q225 -338 277 -336);"/>
                    <Edge cubics="!-384 -460(;-384,-460 -392,-460 -392,-460q-384 -460 -392 -460);"/>
                    <Edge cubics="!-384 -453(;-384,-454 -384,-455 -384,-456q-384 -453Q-384 -455q-384 -456);"/>
                    <Edge cubics="!-359 -459(;-359,-456 -359,-453 -360,-450q-359 -459Q-359 -454q-360 -450);"/>
                    <Edge cubics="!-384 -456(;-384,-457 -384,-458 -384,-460q-384 -456Q-384 -457q-384 -460);"/>
                    <Edge cubics="!-439 -443(;-420,-450 -402,-453 -384,-453q-439 -443Q-411 -453q-384 -453);"/>
                    <Edge cubics="!-416 -493(;-410,-500 -398,-506 -379,-511q-416 -493Q-407 -504q-379 -511);"/>
                    <Edge cubics="!-402 -371(;-408,-373 -412,-376 -415,-380q-402 -371Q-411 -374q-415 -380);"/>
                    <Edge cubics="!-350 -333(;-350,-333 -344,-332 -344,-332q-350 -333 -344 -332);"/>
                    <Edge cubics="!-358 -339(;-355,-338 -352,-336 -350,-333q-358 -339Q-353 -337q-350 -333);"/>
                    <Edge cubics="!-384 -370(;-384,-370 -402,-371 -402,-371q-384 -370 -402 -371);"/>
                    <Edge cubics="!-377 -363(;-377,-363 -384,-370 -384,-370q-377 -363 -384 -370);"/>
                    <Edge cubics="!-451 -480(;-441,-485 -429,-490 -416,-493q-451 -480Q-436 -488q-416 -493);"/>
                    <Edge cubics="!-415 -380(;-434,-381 -445,-386 -449,-396q-415 -380Q-443 -381q-449 -396);"/>
                    <Edge cubics="!-156 -502(;-153,-502 -149,-502 -146,-501q-156 -502Q-151 -502q-146 -501);"/>
                    <Edge cubics="!-224 -496(;-217,-501 -210,-504 -202,-506q-224 -496Q-214 -503q-202 -506);"/>
                    <Edge cubics="!-202 -506(;-185,-510 -170,-509 -156,-502q-202 -506Q-177 -512q-156 -502);"/>
                    <Edge cubics="!-308 -498(;-305,-497 -302,-497 -300,-496q-308 -498Q-303 -497q-300 -496);"/>
                    <Edge cubics="!-253 -446(;-252,-451 -251,-457 -250,-462q-253 -446Q-252 -454q-250 -462);"/>
                    <Edge cubics="!-250 -462(;-248,-467 -246,-471 -243,-475q-250 -462Q-247 -469q-243 -475);"/>
                    <Edge cubics="!-243 -475(;-243,-475 -272,-474 -272,-474q-243 -475 -272 -474);"/>
                    <Edge cubics="!-246 -401(;-247,-404 -248,-406 -249,-408q-246 -401Q-248 -405q-249 -408);"/>
                    <Edge cubics="!-249 -408(;-261,-405 -273,-403 -285,-404q-249 -408Q-267 -403q-285 -404);"/>
                    <Edge cubics="!-285 -404(;-285,-404 -246,-401 -246,-401q-285 -404 -246 -401);"/>
                    <Edge cubics="!-334 -322(;-334,-321 -336,-317 -339,-311q-334 -322Q-334 -320q-339 -311);"/>
                    <Edge cubics="!-260 -369(;-260,-369 -339,-369 -339,-369q-260 -369 -339 -369);"/>
                    <Edge cubics="!-145 -357(;-185,-358 -213,-366 -229,-380q-145 -357Q-205 -359q-229 -380);"/>
                    <Edge cubics="!-229 -380(;-229,-380 -241,-380 -241,-380q-229 -380 -241 -380);"/>
                    <Edge cubics="!-300 -496(;-300,-496 -224,-496 -224,-496q-300 -496 -224 -496);"/>
                    <Edge cubics="!-241 -380(;-242,-375 -245,-372 -249,-370q-241 -380Q-243 -373q-249 -370);"/>
                    <Edge cubics="!-360 -450(;-360,-450 -253,-446 -253,-446q-360 -450 -253 -446);"/>
                    <Edge cubics="!-339 -369(;-339,-366 -341,-363 -346,-360q-339 -369Q-339 -364q-346 -360);"/>
                    <Edge cubics="!-290 -459(;-290,-459 -359,-459 -359,-459q-290 -459 -359 -459);"/>
                    <Edge cubics="!-780 95(;-777,97 -774,99 -773,102q-780 95Q-775 98q-773 102);"/>
                    <Edge cubics="!-781 89(;-780,90 -780,92 -780,95q-781 89Q-780 91q-780 95);"/>
                    <Edge cubics="!-742 145(;-741,147 -741,150 -740,153q-742 145Q-741 148q-740 153);"/>
                    <Edge cubics="!-740 162(;-740,162 -740,153 -740,153q-740 162 -740 153);"/>
                    <Edge cubics="!-740 162(;-741,167 -742,172 -743,177q-740 162Q-741 169q-743 177);"/>
                    <Edge cubics="!-694 135(;-695,130 -693,125 -686,122q-694 135Q-696 127q-686 122);"/>
                    <Edge cubics="!-709 127(;-702,128 -697,131 -694,135q-709 127Q-699 129q-694 135);"/>
                    <Edge cubics="!-740 153(;-740,153 -740,107 -740,107q-740 153 -740 107);"/>
                    <Edge cubics="!-565 123(;-565,123 -562,117 -562,117q-565 123 -562 117);"/>
                    <Edge cubics="!-666 117(;-635,115 -601,117 -565,123q-666 117Q-619 114q-565 123);"/>
                    <Edge cubics="!-600 187(;-636,187 -664,186 -684,184q-600 187Q-654 187q-684 184);"/>
                    <Edge cubics="!-385 -248(;-389,-257 -391,-265 -390,-272q-385 -248Q-391 -262q-390 -272);"/>
                    <Edge cubics="!-410 -299(;-409,-300 -407,-301 -404,-302q-410 -299Q-408 -300q-404 -302);"/>
                    <Edge cubics="!-389 -218(;-385,-225 -382,-231 -380,-235q-389 -218Q-383 -229q-380 -235);"/>
                    <Edge cubics="!-380 -235(;-381,-238 -383,-243 -385,-248q-380 -235Q-382 -240q-385 -248);"/>
                    <Edge cubics="!-385 -23(;-385,-24 -385,-24 -385,-25q-385 -23Q-385 -24q-385 -25);"/>
                    <Edge cubics="!-389 3(;-387,-10 -386,-19 -385,-23q-389 3Q-386 -17q-385 -23);"/>
                    <Edge cubics="!-347 -55(;-346,-50 -346,-46 -345,-41q-347 -55Q-346 -48q-345 -41);"/>
                    <Edge cubics="!-389 -51(;-389,-52 -389,-52 -389,-53q-389 -51Q-389 -52q-389 -53);"/>
                    <Edge cubics="!-346 -56(;-346,-56 -347,-55 -347,-55q-346 -56 -347 -55);"/>
                    <Edge cubics="!-385 32(;-386,31 -386,30 -387,29q-385 32Q-386 30q-387 29);"/>
                    <Edge cubics="!-387 29(;-390,23 -391,14 -389,3q-387 29Q-392 20q-389 3);"/>
                    <Edge cubics="!-531 125(;-530,128 -530,132 -530,135q-531 125Q-530 130q-530 135);"/>
                    <Edge cubics="!-530 135(;-526,138 -524,142 -525,147q-530 135Q-524 140q-525 147);"/>
                    <Edge cubics="!-386 90(;-386,90 -385,32 -385,32q-386 90 -385 32);"/>
                    <Edge cubics="!-285 90(;-285,90 -290,90 -290,90q-285 90 -290 90);"/>
                    <Edge cubics="!-285 96(;-285,96 -285,90 -285,90q-285 96 -285 90);"/>
                    <Edge cubics="!-142 92(;-142,92 -142,96 -142,96q-142 92 -142 96);"/>
                    <Edge cubics="!-290 90(;-290,90 -291,-48 -291,-48q-290 90 -291 -48);"/>
                    <Edge cubics="!-345 -41(;-333,-40 -321,-39 -308,-36q-345 -41Q-327 -40q-308 -36);"/>
                    <Edge cubics="!-389 -53(;-392,-54 -396,-56 -399,-57q-389 -53Q-394 -55q-399 -57);"/>
                    <Edge cubics="!-404 -302(;-409,-306 -412,-311 -413,-316q-404 -302Q-412 -308q-413 -316);"/>
                    <Edge cubics="!-339 -311(;-338,-307 -338,-302 -337,-297q-339 -311Q-338 -305q-337 -297);"/>
                    <Edge cubics="!-684 209(;-684,212 -684,216 -685,220q-684 209Q-684 214q-685 220);"/>
                    <Edge cubics="!-684 206(;-684,207 -684,208 -684,209q-684 206Q-684 207q-684 209);"/>
                    <Edge cubics="!-769 223(;-777,228 -784,228 -789,224q-769 223Q-781 230q-789 224);"/>
                    <Edge cubics="!-789 224(;-789,233 -789,244 -789,256q-789 224Q-789 238q-789 256);"/>
                    <Edge cubics="!-684 184(;-684,184 -684,206 -684,206q-684 184 -684 206);"/>
                    <Edge cubics="!-740 337(;-740,337 -740,162 -740,162q-740 337 -740 162);"/>
                    <Edge cubics="!678 -507(;683,-513 689,-515 697,-513q678 -507Q685 -516q697 -513);"/>
                    <Edge cubics="!697 -513(;703,-512 708,-510 712,-505q697 -513Q706 -512q712 -505);"/>
                    <Edge cubics="!680 -361(;680,-361 673,-364 673,-364q680 -361 673 -364);"/>
                    <Edge cubics="!683 -328(;683,-328 683,-329 683,-329q683 -328 683 -329);"/>
                    <Edge cubics="!676 -331(;676,-331 683,-328 683,-328q676 -331 683 -328);"/>
                    <Edge cubics="!759 -359(;750,-360 740,-360 730,-361q759 -359Q745 -360q730 -361);"/>
                    <Edge cubics="!730 -361(;723,-360 717,-359 711,-359q730 -361Q720 -359q711 -359);"/>
                    <Edge cubics="!712 -505(;733,-504 753,-502 774,-501q712 -505Q743 -503q774 -501);"/>
                    <Edge cubics="!719 -209(;718,-206 718,-204 718,-201q719 -209Q718 -205q718 -201);"/>
                    <Edge cubics="!718 -173(;718,-172 718,-170 719,-169q718 -173Q718 -171q719 -169);"/>
                    <Edge cubics="!678 -124(;676,-129 675,-136 675,-145q678 -124Q675 -131q675 -145);"/>
                    <Edge cubics="!718 -201(;717,-190 717,-180 718,-173q718 -201Q716 -184q718 -173);"/>
                    <Edge cubics="!693 67(;687,67 681,67 676,67q693 67Q684 67q676 67);"/>
                    <Edge cubics="!693 59(;693,59 693,67 693,67q693 59 693 67);"/>
                    <Edge cubics="!698 56(;696,57 694,58 693,59q698 56Q695 57q693 59);"/>
                    <Edge cubics="!676 67(;675,67 673,67 672,68q676 67Q674 67q672 68);"/>
                    <Edge cubics="!277 -336(;278,-335 278,-334 279,-333q277 -336Q278 -335q279 -333);"/>
                    <Edge cubics="!432 -326(;432,-326 432,-317 432,-317q432 -326 432 -317);"/>
                    <Edge cubics="!432 -317(;432,-317 436,-317 436,-317q432 -317 436 -317);"/>
                    <Edge cubics="!450 -353(;450,-353 453,-307 453,-307q450 -353 453 -307);"/>
                    <Edge cubics="!279 -333(;326,-332 377,-329 432,-326q279 -333Q350 -331q432 -326);"/>
                    <Edge cubics="!474 -333(;507,-334 536,-333 562,-331q474 -333Q523 -334q562 -331);"/>
                    <Edge cubics="!562 -331(;562,-331 565,-333 565,-333q562 -331 565 -333);"/>
                    <Edge cubics="!17 -487(;20,-490 24,-493 29,-496q17 -487Q22 -492q29 -496);"/>
                    <Edge cubics="!13 -489(;14,-488 16,-488 17,-487q13 -489Q15 -488q17 -487);"/>
                    <Edge cubics="!41 -375(;32,-366 21,-359 9,-356q41 -375Q27 -361q9 -356);"/>
                    <Edge cubics="!82 -84(;82,-84 107,-78 107,-78q82 -84 107 -78);"/>
                    <Edge cubics="!239 -168(;238,-172 235,-174 230,-174q239 -168Q237 -174q230 -174);"/>
                    <Edge cubics="!240 -120(;240,-120 239,-168 239,-168q240 -120 239 -168);"/>
                    <Edge cubics="!194 -66(;194,-66 202,-66 202,-66q194 -66 202 -66);"/>
                    <Edge cubics="!192 -77(;192,-74 193,-71 194,-66q192 -77Q192 -73q194 -66);"/>
                    <Edge cubics="!107 -78(;107,-78 192,-77 192,-77q107 -78 192 -77);"/>
                    <Edge cubics="!-50 -39(;-49,-39 -47,-39 -46,-38q-50 -39Q-48 -39q-46 -38);"/>
                    <Edge cubics="!-46 -38(;-46,-38 -46,-49 -46,-49q-46 -38 -46 -49);"/>
                    <Edge cubics="!22 91(;22,91 22,96 22,96q22 91 22 96);"/>
                    <Edge cubics="!34 92(;30,92 26,92 22,91q34 92Q28 92q22 91);"/>
                    <Edge cubics="!220 -53(;220,-53 224,-54 224,-54q220 -53 224 -54);"/>
                    <Edge cubics="!138 88(;133,89 127,90 120,91q138 88Q130 90q120 91);"/>
                    <Edge cubics="!120 91(;117,91 103,91 79,91q120 91Q115 91q79 91);"/>
                    <Edge cubics="!203 72(;201,73 199,74 197,75q203 72Q200 74q197 75);"/>
                    <Edge cubics="!197 75(;197,75 197,86 197,86q197 75 197 86);"/>
                    <Edge cubics="!197 86(;197,86 138,88 138,88q197 86 138 88);"/>
                    <Edge cubics="!224 -54(;224,-54 224,-88 224,-88q224 -54 224 -88);"/>
                    <Edge cubics="!79 91(;53,92 38,92 34,92q79 91Q40 92q34 92);"/>
                    <Edge cubics="!560 -122(;558,-123 556,-123 555,-124q560 -122Q557 -123q555 -124);"/>
                    <Edge cubics="!555 -124(;555,-124 552,-124 552,-124q555 -124 552 -124);"/>
                    <Edge cubics="!552 -124(;549,-124 547,-124 544,-124q552 -124Q548 -124q544 -124);"/>
                    <Edge cubics="!475 -68(;475,-68 499,-67 499,-67q475 -68 499 -67);"/>
                    <Edge cubics="!499 -67(;499,-67 499,-78 499,-78q499 -67 499 -78);"/>
                    <Edge cubics="!560 -115(;560,-115 560,-122 560,-122q560 -115 560 -122);"/>
                    <Edge cubics="!544 -124(;544,-124 485,-125 485,-125q544 -124 485 -125);"/>
                    <Edge cubics="!668 -140(;668,-140 668,-113 668,-113q668 -140 668 -113);"/>
                    <Edge cubics="!633 -75(;633,-75 641,-80 641,-80q633 -75 641 -80);"/>
                    <Edge cubics="!499 -78(;546,-78 590,-77 633,-75q499 -78Q569 -78q633 -75);"/>
                    <Edge cubics="!404 -69(;404,-69 404,-78 404,-78q404 -69 404 -78);"/>
                    <Edge cubics="!336 -80(;363,-75 385,-72 404,-69q336 -80Q376 -73q404 -69);"/>
                    <Edge cubics="!458 66(;458,66 447,66 447,66q458 66 447 66);"/>
                    <Edge cubics="!282 85(;282,85 282,87 282,87q282 85 282 87);"/>
                    <Edge cubics="!297 87(;292,87 287,86 282,85q297 87Q289 87q282 85);"/>
                    <Edge cubics="!354 85(;327,87 308,88 297,87q354 85Q313 88q297 87);"/>
                    <Edge cubics="!416 72(;414,73 412,74 409,75q416 72Q413 73q409 75);"/>
                    <Edge cubics="!447 72(;436,72 426,72 416,72q447 72Q431 72q416 72);"/>
                    <Edge cubics="!447 66(;447,66 447,72 447,72q447 66 447 72);"/>
                    <Edge cubics="!558 77(;547,77 537,76 528,75q558 77Q541 77q528 75);"/>
                    <Edge cubics="!528 75(;527,84 525,91 522,96q528 75Q526 88q522 96);"/>
                    <Edge cubics="!475 -165(;475,-165 474,-333 474,-333q475 -165 474 -333);"/>
                    <Edge cubics="!453 -307(;453,-307 460,-198 460,-198q453 -307 460 -198);"/>
                    <Edge cubics="!224 -88(;251,-91 289,-88 336,-80q224 -88Q265 -92q336 -80);"/>
                    <Edge cubics="!675 -145(;672,-144 670,-142 668,-140q675 -145Q671 -143q668 -140);"/>
                    <Edge cubics="!92 -509(;305,-516 501,-516 678,-507q92 -509Q412 -520q678 -507);"/>
                    <Edge cubics="!-67 92(;-67,92 -142,92 -142,92q-67 92 -142 92);"/>
                    <Edge cubics="!-60 -353(;-91,-354 -120,-355 -145,-357q-60 -353Q-107 -354q-145 -357);"/>
                    <Edge cubics="!174 -376(;178,-376 182,-375 184,-372q174 -376Q181 -376q184 -372);"/>
                    <Edge cubics="!133 -367(;123,-363 113,-361 103,-360q133 -367Q120 -362q103 -360);"/>
                    <Edge cubics="!103 -360(;86,-359 70,-362 54,-364q103 -360Q91 -359q54 -364);"/>
                    <Edge cubics="!54 -364(;50,-365 47,-365 44,-367q54 -364Q45 -366q44 -367);"/>
                    <Edge cubics="!186 -334(;190,-332 194,-330 196,-326q186 -334Q194 -330q196 -326);"/>
                    <Edge cubics="!196 -326(;199,-323 200,-318 200,-314q196 -326Q200 -322q200 -314);"/>
                    <Edge cubics="!200 -314(;201,-309 201,-303 200,-298q200 -314Q202 -306q200 -298);"/>
                    <Edge cubics="!200 -298(;200,-294 200,-289 196,-287q200 -298Q200 -289q196 -287);"/>
                    <Edge cubics="!196 -287(;192,-283 186,-285 182,-288q196 -287Q191 -282q182 -288);"/>
                    <Edge cubics="!182 -288(;178,-292 177,-297 175,-302q182 -288Q180 -290q175 -302);"/>
                    <Edge cubics="!175 -302(;174,-308 172,-313 168,-317q175 -302Q173 -312q168 -317);"/>
                    <Edge cubics="!168 -317(;162,-315 156,-314 149,-314q168 -317Q159 -314q149 -314);"/>
                    <Edge cubics="!149 -314(;142,-314 136,-315 131,-320q149 -314Q137 -314q131 -320);"/>
                    <Edge cubics="!131 -320(;128,-322 126,-325 126,-329q131 -320Q126 -323q126 -329);"/>
                    <Edge cubics="!126 -331(;126,-334 127,-337 129,-339q126 -331Q126 -336q129 -339);"/>
                    <Edge cubics="!129 -339(;130,-341 133,-342 136,-342q129 -339Q131 -342q136 -342);"/>
                    <Edge cubics="!136 -342(;136,-342 136,-343 135,-343q136 -342 135 -343);"/>
                    <Edge cubics="!135 -343(;148,-343 160,-342 173,-342q135 -343 173 -342);"/>
                    <Edge cubics="!173 -342(;175,-342 178,-342 180,-341q173 -342 180 -341);"/>
                    <Edge cubics="!44 -367(;41,-370 40,-372 41,-375q44 -367Q39 -371q41 -375);"/>
                    <Edge cubics="!145 -379(;145,-374 141,-370 133,-367q145 -379Q145 -371q133 -367);"/>
                    <Edge cubics="!180 -341(;183,-339 184,-337 185,-334q180 -341Q184 -338q185 -334);"/>
                    <Edge cubics="!185 -334(;185,-334 185,-334 186,-334q185 -334Q185 -334q186 -334);"/>
                    <Edge cubics="!184 -372(;185,-371 185,-370 186,-369q184 -372Q185 -371q186 -369);"/>
                    <Edge cubics="!145 -379(;145,-379 174,-376 174,-376q145 -379 174 -376);"/>
                    <Edge cubics="!-60 -353(;-60,-353 -60,-103 -60,-103q-60 -353 -60 -103);"/>
                    <Edge cubics="!673 -364(;508,-373 346,-374 186,-369q673 -364Q426 -377q186 -369);"/>
                    <Edge cubics="!126 -329(;126,-329 126,-331 126,-331q126 -329 126 -331);"/>
                    <Edge cubics="!326 960(;326,960 325,960 325,960q326 960 325 960);"/>
                    <Edge cubics="!342 935(;337,946 332,955 326,960q342 935Q335 952q326 960);"/>
                    <Edge cubics="!344 954(;336,957 330,959 326,960q344 954Q332 958q326 960);"/>
                    <Edge cubics="!359 944(;356,949 351,952 344,954q359 944Q355 951q344 954);"/>
                    <Edge cubics="!-60 -353(;-60,-353 -15,-353 -15,-353q-60 -353 -15 -353);"/>
                    <Edge cubics="!9 -356(;2,-354 -6,-353 -15,-353q9 -356Q-2 -353q-15 -353);"/>
                    <Edge cubics="!-15 -353(;-15,-353 210,-353 210,-353q-15 -353 210 -353);"/>
                  </edges>
                </DOMShape>
              </elements>
            </DOMFrame>
          </frames>
        </DOMLayer>
      </layers>
    </DOMTimeline>
  </timeline>
</DOMSymbolItem>