<DOMSymbolItem xmlns:xsi="http://www.w3.org/2001/XMLSchema-instance" xmlns="http://ns.adobe.com/xfl/2008/" name="Assets/CGreenHouse Assets/CPlantingBed Assets/SunFlowerSparse_Vector" itemID="5cbf4259-00000293" lastModified="1556038233">
  <timeline>
    <DOMTimeline name="SunFlowerSparse_Vector">
      <layers>
        <DOMLayer name="Layer_1" color="#00FFFF" current="true" isSelected="true">
          <frames>
            <DOMFrame index="0" keyMode="9728">
              <elements>
                <DOMShape>
                  <fills>
                    <FillStyle index="1">
                      <SolidColor color="#FFCC00"/>
                    </FillStyle>
                    <FillStyle index="2">
                      <SolidColor color="#FFE917"/>
                    </FillStyle>
                    <FillStyle index="3">
                      <SolidColor color="#350B00"/>
                    </FillStyle>
                    <FillStyle index="4">
                      <SolidColor color="#006600"/>
                    </FillStyle>
                    <FillStyle index="5">
                      <SolidColor color="#006633"/>
                    </FillStyle>
                  </fills>
                  <strokes>
                    <StrokeStyle index="1">
                      <SolidStroke scaleMode="normal" weight="0.1">
                        <fill>
                          <SolidColor/>
                        </fill>
                      </SolidStroke>
                    </StrokeStyle>
                    <StrokeStyle index="2">
                      <SolidStroke scaleMode="normal">
                        <fill>
                          <SolidColor/>
                        </fill>
                      </SolidStroke>
                    </StrokeStyle>
                    <StrokeStyle index="3">
                      <SolidStroke scaleMode="normal" weight="0.1">
                        <fill>
                          <SolidColor color="#003300"/>
                        </fill>
                      </SolidStroke>
                    </StrokeStyle>
                  </strokes>
                  <edges>
                    <Edge fillStyle1="1" edges="!470 239S2[475 242 479 244"/>
                    <Edge fillStyle0="2" edges="!529 265S1|523 260!523 260[510 253 500 251!500 251[493 246 489 246!489 246[485 244 479 244"/>
                    <Edge fillStyle0="2" fillStyle1="2" strokeStyle="1" edges="!416 318S7[443 322 473 315!473 315[512 306 560 279"/>
                    <Edge fillStyle0="2" strokeStyle="1" edges="!560 279S5|529 265"/>
                    <Edge fillStyle0="2" fillStyle1="2" strokeStyle="1" edges="!529 265S7|500 251"/>
                    <Edge strokeStyle="1" edges="!500 251S4|495 246!495 246[481 244 470 239"/>
                    <Edge fillStyle0="1" strokeStyle="1" edges="!470 239S5[464 239 458 239!458 239[454 237 448 237!448 237|443 237!443 237[441 237 435 237"/>
                    <Edge fillStyle0="2" strokeStyle="1" edges="!435 237S5[398 233 368 249"/>
                    <Edge fillStyle0="2" edges="!464 385S1[462 382 460 378!460 378[454 366 439 352!439 352[425 338 412 327!412 327|425 327!425 327|450 327!450 327[464 325 477 320!477 320[483 318 493 315!493 315[516 306 548 292!548 292[558 288 560 279"/>
                    <Edge fillStyle0="2" fillStyle1="1" edges="!479 244S3[495 251 518 262!518 262[529 267 533 274!533 274[539 286 531 290!531 290[527 290 512 286!512 286|502 279!502 279[468 262 452 260!452 260[439 258 420 262!420 262[400 262 391 262!391 262[385 251 391 244!391 244[393 239 402 239
!402 239[420 237 435 237"/>
                    <Edge fillStyle0="2" fillStyle1="2" strokeStyle="1" edges="
!370 394S7[383 405 398 414!398 414[433 437 485 454"/>
                    <Edge fillStyle0="2" strokeStyle="1" edges="
!485 454S5|475 419"/>
                    <Edge fillStyle0="2" fillStyle1="2" strokeStyle="1" edges="
!475 419S7|464 389"/>
                    <Edge fillStyle0="2" strokeStyle="1" edges="
!464 389S5|464 385"/>
                    <Edge strokeStyle="1" edges="
!464 385S4|464 382!464 382[448 350 425 327"/>
                    <Edge fillStyle0="2" fillStyle1="2" strokeStyle="1" edges="
!425 327S7[420 322 416 318!416 318[412 313 406 311!406 311[389 299 370 292"/>
                    <Edge fillStyle0="2" edges="
!475 419S1|475 410!475 410[470 398 464 389!368 401|373 405!373 405|375 408!375 408[385 414 398 421!398 421[406 426 414 431!414 431[437 440 466 451!466 451[481 456 485 454"/>
                    <Edge fillStyle0="2" fillStyle1="1" edges="
!335 81S3[341 71 345 67!345 67|350 62!350 62|356 53!356 53|358 46!358 46|385 14!385 14|387 14!387 14[398 28 385 41!385 41|366 62!366 62|333 113!333 113|329 122!329 122|329 131!329 131[327 138 323 140!323 140[325 152 323 161!323 161|320
 168!320 168|323 177!323 177[325 186 325 196"/>
                    <Edge fillStyle0="2" fillStyle1="2" strokeStyle="1" edges="
!364 205S7[368 193 375 184"/>
                    <Edge fillStyle0="2" strokeStyle="1" edges="
!375 184S5[381 175 387 168!387 168[389 166 391 163!391 163[418 99 393 5!393 5|385 14!385 14|366 34!366 34[354 46 350 53!350 53|350 55!350 55|345 58!345 58|343 60!343 60|343 62"/>
                    <Edge strokeStyle="1" edges="
!343 62S4[325 92 316 120"/>
                    <Edge fillStyle1="1" edges="
!318 124S2|320 117!320 117[323 108 325 104!325 104[329 94 331 90!331 90|333 83!333 83|335 81"/>
                    <Edge fillStyle0="2" edges="
!343 62S1[339 69 335 81!318 124[316 122 316 120!316 120[316 115 314 110!314 110[312 97 308 83!308 83[308 74 304 67!304 67[293 44 281 14!281 14[275 0 268 0"/>
                    <Edge strokeStyle="1" edges="
!223 122S4[225 94 235 64"/>
                    <Edge fillStyle1="2" strokeStyle="1" edges="
!235 64S6|237 60"/>
                    <Edge fillStyle0="2" fillStyle1="2" strokeStyle="1" edges="
!237 60S7|252 32"/>
                    <Edge fillStyle1="2" strokeStyle="1" edges="
!252 32S6|268 0"/>
                    <Edge fillStyle0="2" fillStyle1="2" strokeStyle="1" edges="
!268 0S7[293 46 304 87!304 87[312 129 304 168!304 168[300 182 293 196"/>
                    <Edge fillStyle0="2" edges="
!252 32S1|248 37!248 37[241 48 237 60"/>
                    <Edge fillStyle1="2" edges="
!233 157S2[229 145 223 138!223 138[221 133 218 129!218 129|218 115!218 115[219 116 220 117!220 117|223 122!223 122|233 138!233 138[231 122 231 104!231 104[231 83 235 69!235 69[235 67 235 64"/>
                    <Edge fillStyle1="2" strokeStyle="1" edges="
!243 212S6|243 210!243 210[243 203 243 193!243 193[243 184 239 175!239 175[237 168 235 161!235 161|235 159!235 159|233 157"/>
                    <Edge fillStyle0="2" fillStyle1="1" edges="
!212 230S3[212 235 208 235!208 235|206 235!206 235[198 233 195 230!195 230[187 223 183 223!183 223|183 221!183 221[177 221 175 219!175 219|168 214!168 214|162 214!162 214|160 212!160 212[158 210 150 210!150 210|148 205!148 205|135 203
!135 203[135 200 131 200!131 200|106 198!106 198|106 196!106 196|73 193"/>
                    <Edge fillStyle1="1" edges="
!73 193S2|60 191!60 191[56 182 60 175"/>
                    <Edge fillStyle0="2" fillStyle1="1" edges="
!60 175S3[60 173 60 170!60 170[85 168 106 173!106 173[110 173 108 175!108 175|131 177!131 177[141 182 148 182!148 182|152 186!152 186[156 184 160 189!160 189|173 193!173 193[177 193 183 200!183 200|185 200!185 200|187 203!187 203[193
 203 198 210!198 210[206 210 210 214!210 214[214 223 212 230"/>
                    <Edge fillStyle1="3" strokeStyle="2" edges="
!362 237S6[366 242 368 249"/>
                    <Edge fillStyle0="2" fillStyle1="3" strokeStyle="2" edges="
!368 249S7[373 262 373 279!373 279[373 286 370 292!370 292[368 315 350 334!350 334|350 336!350 336[333 350 314 357!314 357[304 359 291 359!291 359[285 359 281 359!281 359[275 357 270 357!270 357[258 352 248 345!248 345[241 341 235 336
!235 336[223 320 216 306!216 306[212 292 212 279!212 279[212 276 212 274!212 274[214 249 227 230"/>
                    <Edge fillStyle1="3" strokeStyle="2" edges="
!227 230S6[231 226 235 221!235 221[241 214 243 212"/>
                    <Edge fillStyle0="2" fillStyle1="3" strokeStyle="2" edges="
!243 212S7[266 196 291 196!291 196|293 196!293 196[302 196 308 198"/>
                    <Edge fillStyle1="3" strokeStyle="2" edges="
!308 198S6[314 200 316 200"/>
                    <Edge fillStyle0="2" strokeStyle="1" edges="
!227 230S5[223 226 218 221!218 221[195 198 164 186!164 186[158 184 152 182!152 182|150 182!150 182[108 168 56 168!56 168|60 175"/>
                    <Edge fillStyle0="3" fillStyle1="3" strokeStyle="1" edges="
!268 233S7|258 239"/>
                    <Edge fillStyle0="2" fillStyle1="1" edges="
!314 193S3[310 184 310 175!310 175[310 161 314 154!314 154|316 129!316 129|318 124"/>
                    <Edge fillStyle1="1" edges="
!325 196S2[323 198 323 203"/>
                    <Edge fillStyle0="3" fillStyle1="1" edges="
!323 203S3|320 205!320 205[316 203 316 200"/>
                    <Edge fillStyle1="1" edges="
!316 200S2|316 198!316 198[314 196 314 193"/>
                    <Edge fillStyle0="2" edges="
!308 198S1[310 196 314 193"/>
                    <Edge fillStyle1="3" strokeStyle="2" edges="
!323 203S6|325 205"/>
                    <Edge fillStyle0="2" fillStyle1="3" strokeStyle="2" edges="
!325 205S7[337 210 348 221!348 221|350 221!350 221[352 223 354 226"/>
                    <Edge fillStyle1="3" strokeStyle="2" edges="
!354 226S6[354 228 356 228!356 228|358 230"/>
                    <Edge fillStyle0="2" edges="
!325 196S1|325 205"/>
                    <Edge fillStyle0="3" fillStyle1="3" strokeStyle="1" edges="
!333 228S7|333 239"/>
                    <Edge fillStyle0="2" strokeStyle="1" edges="
!362 210S5|364 207"/>
                    <Edge fillStyle0="2" edges="
!364 207S1|364 205!364 205[366 200 370 193!370 193|375 184"/>
                    <Edge fillStyle1="3" edges="
!358 230S2|358 233!358 233[358 237 362 237"/>
                    <Edge fillStyle1="2" strokeStyle="1" edges="
!362 210S6[358 216 356 223"/>
                    <Edge strokeStyle="1" edges="
!356 223S4[356 226 356 228"/>
                    <Edge fillStyle0="2" edges="
!354 226S1|356 223"/>
                    <Edge fillStyle0="2" fillStyle1="2" strokeStyle="1" edges="
!348 221S7[356 214 362 210"/>
                    <Edge fillStyle0="2" edges="
!75 196S1|77 203!77 203[85 216 91 223"/>
                    <Edge fillStyle0="2" strokeStyle="1" edges="
!73 193S5|75 196"/>
                    <Edge fillStyle0="2" fillStyle1="2" strokeStyle="1" edges="
!75 196S7|91 223"/>
                    <Edge fillStyle0="2" strokeStyle="1" edges="
!91 223S5|95 228!95 228[95 230 98 230!98 230[98 233 100 233"/>
                    <Edge strokeStyle="1" edges="
!100 233S4[125 260 152 276"/>
                    <Edge fillStyle0="2" fillStyle1="2" strokeStyle="1" edges="
!212 274S7[206 274 200 274!200 274[185 274 173 276!173 276[170 276 168 279"/>
                    <Edge fillStyle0="2" edges="
!100 233S1[108 239 127 251!127 251[148 262 162 272!162 272|152 276!152 276|145 276"/>
                    <Edge fillStyle0="2" fillStyle1="1" edges="
!145 276S3|168 279!168 279|173 279!173 279|195 281!195 281[202 290 195 302!195 302|179 302!179 302|173 299!173 299|150 299!150 299|102 318!102 318|98 322!98 322|91 327!91 327[87 327 83 332!83 332|79 334!79 334|64 348!64 348[60 352 56
 355"/>
                    <Edge fillStyle1="1" edges="
!56 355S2|54 355"/>
                    <Edge fillStyle0="2" fillStyle1="1" edges="
!54 355S3|54 345!54 345|54 341"/>
                    <Edge fillStyle1="1" edges="
!54 341S2|52 338!52 338|58 327!58 327|85 304!85 304|116 286!116 286|135 281!135 281|145 276"/>
                    <Edge fillStyle0="2" strokeStyle="1" edges="
!56 355S5|81 359"/>
                    <Edge fillStyle0="2" fillStyle1="2" strokeStyle="1" edges="
!81 359S7|110 366"/>
                    <Edge fillStyle0="2" strokeStyle="1" edges="
!110 366S5|116 366"/>
                    <Edge strokeStyle="1" edges="
!116 366S4[141 368 166 364"/>
                    <Edge fillStyle0="2" edges="
!116 366S1[118 366 123 366!123 366[135 366 156 361!156 361[160 359 168 359!168 359[166 361 166 364!166 364[162 373 160 385!160 385[160 391 158 403!158 403[152 426 150 458!150 458[150 472 154 477"/>
                    <Edge fillStyle0="2" fillStyle1="2" strokeStyle="1" edges="
!216 306S7[212 309 208 313!208 313[191 332 179 355!179 355[177 359 175 361!175 361[173 373 168 382!168 382[154 424 154 477"/>
                    <Edge fillStyle0="2" strokeStyle="1" edges="
!154 477S5|160 474"/>
                    <Edge fillStyle0="2" edges="
!81 359S1|87 361!87 361[100 366 110 366"/>
                    <Edge fillStyle0="2" fillStyle1="2" strokeStyle="1" edges="
!54 345S7[50 348 45 352"/>
                    <Edge fillStyle0="2" strokeStyle="1" edges="
!45 352S5|54 355"/>
                    <Edge fillStyle0="2" edges="
!54 341S1[45 348 45 352"/>
                    <Edge fillStyle0="2" fillStyle1="1" edges="
!160 426S3|168 394!168 394|175 385!175 385|179 371!179 371|206 322!206 322|208 320!208 320[212 334 210 341!210 341|204 352!204 352|193 366!193 366|193 373!193 373[193 378 189 382!189 382|175 419!175 419|173 426!173 426[173 433 168 442
!168 442|166 451!166 451|166 461!166 461[168 465 166 467"/>
                    <Edge fillStyle1="1" edges="
!166 467S2[166 472 164 474!164 474|160 474"/>
                    <Edge fillStyle0="2" fillStyle1="1" edges="
!160 474S3[158 470 158 461!158 461|160 426"/>
                    <Edge fillStyle0="2" strokeStyle="1" edges="
!166 467S5|183 458"/>
                    <Edge strokeStyle="1" edges="
!183 458S4|193 454"/>
                    <Edge fillStyle0="2" strokeStyle="1" edges="
!193 454S5|210 440"/>
                    <Edge strokeStyle="1" edges="
!210 440S4|216 437!216 437[220 433 225 431"/>
                    <Edge fillStyle0="2" edges="
!183 458S1|189 454!189 454[191 454 193 454"/>
                    <Edge fillStyle0="3" fillStyle1="3" strokeStyle="1" edges="
!329 265S7[331 272 331 279!337 251[337 256 329 265!323 262|329 262!329 262|329 265!316 262|323 262!323 262[316 269 312 262!312 262[314 262 316 262!327 311|314 315"/>
                    <Edge fillStyle0="2" fillStyle1="2" strokeStyle="1" edges="
!350 334S7[354 338 356 345"/>
                    <Edge fillStyle0="2" fillStyle1="1" strokeStyle="1" edges="
!356 345S7|358 348!358 348[362 355 366 368!366 368[366 371 367 374!367 374|368 377!368 377|368 379"/>
                    <Edge fillStyle0="2" fillStyle1="2" strokeStyle="1" edges="
!368 379S7[#170.38 #181.E 370 393"/>
                    <Edge fillStyle0="2" fillStyle1="1" edges="
!368 410S3[368 442 366 470!366 470|366 472"/>
                    <Edge fillStyle1="1" edges="
!366 472S2[364 481 364 488!364 488[362 493 360 497"/>
                    <Edge fillStyle0="2" fillStyle1="1" edges="
!360 497S3[358 500 356 500!356 500[356 495 356 488!356 488[356 479 356 465!356 465[360 442 360 431!360 431[364 396 352 364!352 364[350 350 356 345"/>
                    <Edge fillStyle0="3" fillStyle1="3" strokeStyle="1" edges="
!281 279S7|291 283!291 283[298 288 302 292!302 292|293 315!289 256|300 256!300 256[306 260 312 262!245 239|237 256!237 256[243 258 250 260"/>
                    <Edge fillStyle0="2" fillStyle1="2" strokeStyle="1" edges="
!281 359S7[281 385 289 410!289 410[293 421 300 433!300 433|302 435!302 435|302 437!302 437[308 454 320 467!320 467[329 479 337 488!337 488[345 500 356 509!356 509|358 511"/>
                    <Edge fillStyle0="2" fillStyle1="4" strokeStyle="1" edges="
!358 511S7|358 509"/>
                    <Edge fillStyle0="2" strokeStyle="1" edges="
!358 509S5|360 497"/>
                    <Edge fillStyle0="2" fillStyle1="2" strokeStyle="1" edges="
!248 345S7[233 378 231 417!231 417|231 419!231 419[229 421 231 424!231 424[229 454 237 488!237 488[239 498 242 508!242 508[242 510 243 511"/>
                    <Edge fillStyle0="2" strokeStyle="1" edges="
!243 511S5|264 484"/>
                    <Edge fillStyle0="2" fillStyle1="2" strokeStyle="1" edges="
!264 484S7|285 461"/>
                    <Edge fillStyle0="2" strokeStyle="1" edges="
!285 461S5|287 461!287 461|289 458"/>
                    <Edge fillStyle0="2" edges="
!210 440S1[216 435 218 433!218 433[223 431 225 428!225 428|225 431!225 431[225 433 225 437!225 437[227 458 233 488!233 488[233 490 233 495!233 495[234 504 239 508!239 508[241 510 243 511"/>
                    <Edge fillStyle0="2" fillStyle1="4" edges="
!289 457.5S3[#121.3C #1C7.C4 291 454!291 454|291 451!291 451[293 447 298 440!298 440|298 442!298 442[302 449 308 456!308 456[312 465 320 474"/>
                    <Edge fillStyle0="2" edges="
!320 474S1[327 481 333 488!333 488[337 495 343 500!343 500[350 507 354 511"/>
                    <Edge fillStyle0="2" fillStyle1="4" strokeStyle="1" edges="
!289 458S7|289 457.5"/>
                    <Edge fillStyle0="4" fillStyle1="4" strokeStyle="1" edges="
!289 457.5S7[289.25 456 291 456!291 456[293 449 298 442"/>
                    <Edge fillStyle0="2" edges="
!264 484S1|270 479!270 479[281 470 285 461"/>
                    <Edge fillStyle0="2" fillStyle1="1" edges="
!368 379S3[368 #180.E 368 391!368 391[368 396 368 401"/>
                    <Edge fillStyle0="2" fillStyle1="2" strokeStyle="1" edges="
!368 391S7[369 391 370 393!370 393|370 394"/>
                    <Edge fillStyle0="2" edges="
!371 446S1[373 439 373 433!373 433[373 426 368 410"/>
                    <Edge fillStyle1="1" edges="
!368 401S2[368 405 368 410"/>
                    <Edge fillStyle0="2" strokeStyle="1" edges="
!366 472S5|370 447!370 447|371 446"/>
                    <Edge strokeStyle="1" edges="
!371 446S4|373 440!373 440[375 421 373 405"/>
                    <Edge fillStyle0="2" fillStyle1="2" strokeStyle="1" edges="
!373 405S7[373 398 370 394"/>
                    <Edge fillStyle0="3" fillStyle1="3" strokeStyle="1" edges="
!304 327S7|275 327!316 244|316 262"/>
                    <Edge fillStyle1="4" strokeStyle="1" edges="
!362 507S6[364 507 366 507!366 507[391 502 437 502"/>
                    <Edge fillStyle1="4" edges="
!358 509S2[360 509 362 507"/>
                    <Edge fillStyle1="4" strokeStyle="1" edges="
!362 555S6|360 555!360 555|359.5 554.5"/>
                    <Edge fillStyle0="4" fillStyle1="4" strokeStyle="1" edges="
!373 537S7|395 518!395 518[414 520 416 513!416 513|437 502"/>
                    <Edge fillStyle1="4" edges="
!320 518S2|329 516!329 516|333 513!333 513[345 513 352 511!352 511|354 511"/>
                    <Edge fillStyle0="4" fillStyle1="4" strokeStyle="1" edges="
!323 525S7|320 525!320 525|320 530"/>
                    <Edge fillStyle1="4" strokeStyle="1" edges="
!320 530S6|320 1306!320 1306|289 1306!289 1306|289 578!320 474|320 518"/>
                    <Edge fillStyle0="4" fillStyle1="4" strokeStyle="1" edges="
!320 518S7[320 523 323 525"/>
                    <Edge fillStyle1="4" edges="
!352 548S2[345 541 335 537!335 537[331 532 325 530!325 530|320 530"/>
                    <Edge fillStyle0="4" fillStyle1="4" strokeStyle="1" edges="
!323 525S7[323 527 325 530"/>
                    <Edge strokeStyle="1" edges="
!325 530S4[329 539 341 546!341 546[#15D.B7 #225.DF 359.5 554.5"/>
                    <Edge fillStyle1="4" strokeStyle="1" edges="
!359.5 554.5S6[#163.B #228.9C 352 548"/>
                    <Edge fillStyle0="2" fillStyle1="4" edges="
!354 511S3[356 511 358 511"/>
                    <Edge fillStyle0="4" fillStyle1="4" strokeStyle="1" edges="
!373 537S7|391 557!373 537|323 525!362 555[375 557 391 557"/>
                    <Edge fillStyle0="4" strokeStyle="1" edges="
!260 550S5[258 550 256 550!256 550[252 550 248 550"/>
                    <Edge fillStyle0="4" edges="
!289 557S1|287 555!287 555|285 555!285 555[282 555 280 555!280 555[273 555 268 555!268 555|264 553!264 553[262 553 260 550"/>
                    <Edge fillStyle0="4" fillStyle1="4" strokeStyle="1" edges="
!289 557S7|285 555"/>
                    <Edge strokeStyle="1" edges="
!285 555S4|264 553!264 553[260 543 248 550"/>
                    <Edge fillStyle0="4" fillStyle1="4" strokeStyle="1" edges="
!248 578S7|225 562!225 562[208 562 206 555!206 555|183 543!183 543|150 543"/>
                    <Edge fillStyle0="4" edges="
!287 578S1|289 578"/>
                    <Edge fillStyle0="4" strokeStyle="1" edges="
!210 622S5[237 610 260 596!260 596[264 594 268 592!268 592[270 589 273 589!273 589[273 587 275 587!275 587[277 585 280 583!280 583[282 581 285 580!285 580|285 578!285 578|287 578"/>
                    <Edge fillStyle0="4" fillStyle1="4" strokeStyle="1" edges="
!287 578S7|302 569!302 569|289 557!248 578|302 569!248 578|210 622!191 592|166 587!166 587|166 573!166 573|148 573!148 573[133 564 127 566!127 566|83 566!168 596|154 615!154 615|135 615!135 615|135 626!135 626|112 626!112 626[106 638
 102 638!102 638[93 645 91 654!179 594|191 592!179 594|168 594!168 594|168 596!168 596|179 594"/>
                    <Edge fillStyle0="4" strokeStyle="1" edges="
!248 550S5[218 543 173 541!173 541[160 541 150 543"/>
                    <Edge fillStyle1="5" edges="
!10 635S2[8 632 7 630!7 630[6 627 6 624!6 624[11 621 15 616!15 616|16 615!16 615|16 616!16 616[17 616 19 617!19 617[21 613 26 608"/>
                    <Edge fillStyle0="4" fillStyle1="5" edges="
!31 604S3|32 603!32 603[36 603 39 603!39 603[42 602 43 601!43 601[47 597 49 596!49 596|50 594!50 594[55 593 57 599!57 599[58 600 58 602!58 602[58 608 53 613!53 613[50 618 43 622!43 622[41 622 39 623!39 623|34 626!34 626[37 627 40 628
!40 628|56 633!56 633|62 638!62 638[62 639 63 641!63 641[62 644 61 650!61 650|60 653!60 653|49 653!49 653|42 653!42 653|39 652!39 652|38 652!38 652|33 647!33 647[32 646 31 646"/>
                    <Edge fillStyle1="5" edges="
!31 646S2[30 645 29 645!29 645[27 644 23 644!23 644[21 643 20 643"/>
                    <Edge fillStyle0="4" fillStyle1="4" strokeStyle="1" edges="
!49 596S7|41 594"/>
                    <Edge fillStyle0="4" fillStyle1="4" strokeStyle="3" edges="
!39 603S7[36 602 31 603"/>
                    <Edge fillStyle0="4" strokeStyle="3" edges="
!31 603S5|31 604"/>
                    <Edge fillStyle0="5" strokeStyle="3" edges="
!31 604S5[29 605 27 607!27 607|26 608"/>
                    <Edge strokeStyle="3" edges="
!26 608S4[21 611 16 616"/>
                    <Edge fillStyle0="4" strokeStyle="1" edges="
!41 594S5[37 599 31 603"/>
                    <Edge strokeStyle="1" edges="
!41 594S4|16 615"/>
                    <Edge fillStyle0="4" fillStyle1="4" strokeStyle="1" edges="
!98 610S7|57 599"/>
                    <Edge fillStyle0="5" fillStyle1="5" strokeStyle="1" edges="
!57 599S7|6 624"/>
                    <Edge strokeStyle="1" edges="
!6 624S4[4 625 1 627!1 627|0 627"/>
                    <Edge fillStyle0="4" strokeStyle="1" edges="
!83 566S5[62 578 41 594"/>
                    <Edge fillStyle0="4" fillStyle1="4" strokeStyle="1" edges="
!60 653S7|91 654"/>
                    <Edge strokeStyle="3" edges="
!7 630S4[4 628 0 627!0 627|10 635"/>
                    <Edge fillStyle0="5" strokeStyle="3" edges="
!10 635S5|20 643"/>
                    <Edge strokeStyle="3" edges="
!20 643S4|31 652"/>
                    <Edge fillStyle0="4" fillStyle1="4" strokeStyle="1" edges="
!49 653S7|45 656"/>
                    <Edge fillStyle0="4" fillStyle1="4" strokeStyle="3" edges="
!31 652S7|42 653"/>
                    <Edge fillStyle0="4" fillStyle1="4" strokeStyle="1" edges="
!38 652S7|31 652"/>
                    <Edge fillStyle0="4" strokeStyle="1" edges="
!31 652S5[35 654 45 656"/>
                    <Edge fillStyle1="4" strokeStyle="3" edges="
!31 652S6|31 646"/>
                    <Edge strokeStyle="3" edges="
!31 652S4[30 648 29 645"/>
                    <Edge fillStyle0="4" strokeStyle="1" edges="
!45 656S5[62 659 91 654"/>
                    <Edge fillStyle0="4" fillStyle1="4" strokeStyle="1" edges="
!98 610S7|63 641!43 622|98 610"/>
                    <Edge fillStyle0="4" strokeStyle="1" edges="
!150 543S5[116 548 83 566"/>
                    <Edge fillStyle0="4" fillStyle1="4" strokeStyle="1" edges="
!98 610S7|168 596"/>
                    <Edge fillStyle0="4" strokeStyle="1" edges="
!91 654S5[112 652 139 645!139 645[179 633 210 622"/>
                    <Edge fillStyle0="4" fillStyle1="4" strokeStyle="1" edges="
!191 592S7|248 578!525 566|581 550"/>
                    <Edge fillStyle1="4" strokeStyle="1" edges="
!539 523S6[560 534 581 550"/>
                    <Edge fillStyle0="4" fillStyle1="4" strokeStyle="1" edges="
!452 553S7|466 573!466 573|485 573!485 573|485 585!485 585|508 585!508 585[516 596 518 596!518 596[529 603 531 612"/>
                    <Edge fillStyle1="4" strokeStyle="1" edges="
!448.5 500S6|473 500!473 500[491 502 512 511!512 511[525 516 539 523!625 587[618 592 591 608!591 608[585 610 577 612"/>
                    <Edge fillStyle0="4" fillStyle1="4" strokeStyle="1" edges="
!525 566S7|577 612"/>
                    <Edge fillStyle1="4" strokeStyle="1" edges="
!577 612S6[560 615 531 612"/>
                    <Edge fillStyle0="4" fillStyle1="4" strokeStyle="1" edges="
!429 548S7|456 546!456 546|456 530!456 530|475 530!475 530[489 523 495 523!495 523|539 523!452 553|429 548"/>
                    <Edge fillStyle1="4" strokeStyle="1" edges="
!437 502S6|437 500!437 500|448.5 500"/>
                    <Edge fillStyle0="4" fillStyle1="4" strokeStyle="1" edges="
!437 502S7[#1BA.A #1F4.2 448.5 500"/>
                    <Edge fillStyle1="4" strokeStyle="1" edges="
!531 612S6[510 608 481 601!481 601[443 589 410 578"/>
                    <Edge fillStyle0="4" fillStyle1="4" strokeStyle="1" edges="
!525 566S7|452 553"/>
                    <Edge fillStyle1="4" strokeStyle="1" edges="
!581 550S6[604 566 625 587"/>
                    <Edge fillStyle0="4" fillStyle1="4" strokeStyle="1" edges="
!625 587S7|525 566!391 557|410 578"/>
                    <Edge fillStyle1="4" strokeStyle="1" edges="
!410 578S6[383 566 362 555"/>
                    <Edge fillStyle0="4" fillStyle1="4" strokeStyle="1" edges="
!429 548S7|373 537"/>
                    <Edge fillStyle1="4" strokeStyle="1" edges="
!289 557S6|289 458"/>
                    <Edge cubics="!320 1306(;320,1306 289,1306 289,1306q320 1306 289 1306);"/>
                    <Edge cubics="!625 587(;620,589 608,596 591,608q625 587Q618 592q591 608);"/>
                    <Edge cubics="!329 516(;331,516 333,516 333,513q329 516Q333 513q333 513);"/>
                    <Edge cubics="!333 513(;339,513 345,513 352,511q333 513Q345 513q352 511);"/>
                    <Edge cubics="!320 530(;320,527 320,527 320,525q320 530Q320 527q320 525);"/>
                    <Edge cubics="!362 507(;364,507 364,507 366,507q362 507Q364 507q366 507);"/>
                    <Edge cubics="!352 548(;350,543 343,539 335,537q352 548Q345 541q335 537);"/>
                    <Edge cubics="!539 523(;552,530 566,539 581,550q539 523Q560 534q581 550);"/>
                    <Edge cubics="!456 530(;456,530 475,530 475,530q456 530 475 530);"/>
                    <Edge cubics="!456 546(;456,546 456,530 456,530q456 546 456 530);"/>
                    <Edge cubics="!452 553(;452,553 466,573 466,573q452 553 466 573);"/>
                    <Edge cubics="!429 548(;429,548 456,546 456,546q429 548 456 546);"/>
                    <Edge cubics="!525 566(;525,566 452,553 452,553q525 566 452 553);"/>
                    <Edge cubics="!466 573(;466,573 485,573 485,573q466 573 485 573);"/>
                    <Edge cubics="!475 530(;485,525 491,523 495,523q475 530Q489 523q495 523);"/>
                    <Edge cubics="!373 537(;373,537 395,518 395,518q373 537 395 518);"/>
                    <Edge cubics="!410 578(;391,571 377,562 362,555q410 578Q383 566q362 555);"/>
                    <Edge cubics="!395 518(;408,520 414,518 416,513q395 518Q414 520q416 513);"/>
                    <Edge cubics="!429 548(;429,548 373,537 373,537q429 548 373 537);"/>
                    <Edge cubics="!525 566(;525,566 581,550 581,550q525 566 581 550);"/>
                    <Edge cubics="!495 523(;495,523 539,523 539,523q495 523 539 523);"/>
                    <Edge cubics="!508 585(;514,592 518,596 518,596q508 585Q516 596q518 596);"/>
                    <Edge cubics="!518 596(;525,601 531,606 531,612q518 596Q529 603q531 612);"/>
                    <Edge cubics="!531 612(;516,610 500,606 481,601q531 612Q510 608q481 601);"/>
                    <Edge cubics="!485 585(;485,585 508,585 508,585q485 585 508 585);"/>
                    <Edge cubics="!581 550(;595,562 610,573 625,587q581 550Q604 566q625 587);"/>
                    <Edge cubics="!625 587(;625,587 525,566 525,566q625 587 525 566);"/>
                    <Edge cubics="!481 601(;456,594 433,585 410,578q481 601Q443 589q410 578);"/>
                    <Edge cubics="!485 573(;485,573 485,585 485,585q485 573 485 585);"/>
                    <Edge cubics="!577 612(;564,615 550,615 531,612q577 612Q560 615q531 612);"/>
                    <Edge cubics="!591 608(;587,610 581,612 577,612q591 608Q585 610q577 612);"/>
                    <Edge cubics="!525 566(;525,566 577,612 577,612q525 566 577 612);"/>
                    <Edge cubics="!320 518(;320,518 329,516 329,516q320 518 329 516);"/>
                    <Edge cubics="!320 530(;320,530 320,1306 320,1306q320 530 320 1306);"/>
                    <Edge cubics="!268 555(;268,555 266,553 264,553q268 555 264 553);"/>
                    <Edge cubics="!260 550(;258,550 258,550 256,550q260 550Q258 550q256 550);"/>
                    <Edge cubics="!264 553(;262,553 260,553 260,550q264 553Q262 553q260 550);"/>
                    <Edge cubics="!83 566(;68,573 56,583 41,594q83 566Q62 578q41 594);"/>
                    <Edge cubics="!183 543(;183,543 150,543 150,543q183 543 150 543);"/>
                    <Edge cubics="!173 541(;164,541 158,541 150,543q173 541Q160 541q150 543);"/>
                    <Edge cubics="!179 594(;179,594 191,592 191,592q179 594 191 592);"/>
                    <Edge cubics="!166 573(;166,573 148,573 148,573q166 573 148 573);"/>
                    <Edge cubics="!166 587(;166,587 166,573 166,573q166 587 166 573);"/>
                    <Edge cubics="!168 596(;168,596 154,615 154,615q168 596 154 615);"/>
                    <Edge cubics="!168 594(;168,594 168,596 168,596q168 594 168 596);"/>
                    <Edge cubics="!179 594(;179,594 168,594 168,594q179 594 168 594);"/>
                    <Edge cubics="!191 592(;191,592 166,587 166,587q191 592 166 587);"/>
                    <Edge cubics="!168 596(;168,596 179,594 179,594q168 596 179 594);"/>
                    <Edge cubics="!98 610(;98,610 168,596 168,596q98 610 168 596);"/>
                    <Edge cubics="!154 615(;154,615 135,615 135,615q154 615 135 615);"/>
                    <Edge cubics="!148 573(;137,566 131,564 127,566q148 573Q133 564q127 566);"/>
                    <Edge cubics="!248 578(;248,578 210,622 210,622q248 578 210 622);"/>
                    <Edge cubics="!248 578(;248,578 225,562 225,562q248 578 225 562);"/>
                    <Edge cubics="!210 622(;229,612 243,606 260,596q210 622Q237 610q260 596);"/>
                    <Edge cubics="!225 562(;214,562 206,560 206,555q225 562Q208 562q206 555);"/>
                    <Edge cubics="!191 592(;191,592 248,578 248,578q191 592 248 578);"/>
                    <Edge cubics="!206 555(;206,555 183,543 183,543q206 555 183 543);"/>
                    <Edge cubics="!127 566(;127,566 83,566 83,566q127 566 83 566);"/>
                    <Edge cubics="!150 543(;127,546 106,555 83,566q150 543Q116 548q83 566);"/>
                    <Edge cubics="!112 626(;108,636 104,638 102,638q112 626Q106 638q102 638);"/>
                    <Edge cubics="!102 638(;95,642 91,649 91,654q102 638Q93 645q91 654);"/>
                    <Edge cubics="!91 654(;106,652 120,649 139,645q91 654Q112 652q139 645);"/>
                    <Edge cubics="!135 626(;135,626 112,626 112,626q135 626 112 626);"/>
                    <Edge cubics="!139 645(;166,636 189,629 210,622q139 645Q179 633q210 622);"/>
                    <Edge cubics="!135 615(;135,615 135,626 135,626q135 615 135 626);"/>
                    <Edge cubics="!31 652(;33,652 39,654 45,656q31 652Q35 654q45 656);"/>
                    <Edge cubics="!45 656(;56,656 70,656 91,654q45 656Q62 659q91 654);"/>
                    <Edge cubics="!289 557(;287,555 287,555 287,555q289 557Q287 555q287 555);"/>
                    <Edge cubics="!289 1306(;289,1306 289,578 289,578q289 1306 289 578);"/>
                    <Edge cubics="!281 14(;277,7 275,0 268,0q281 14Q275 0q268 0);"/>
                    <Edge cubics="!235 69(;231,83 231,92 231,104q235 69Q231 83q231 104);"/>
                    <Edge cubics="!252 32(;252,32 237,60 237,60q252 32 237 60);"/>
                    <Edge cubics="!252 32(;252,32 248,37 248,37q252 32 248 37);"/>
                    <Edge cubics="!237 60(;237,60 235,64 235,64q237 60 235 64);"/>
                    <Edge cubics="!248 37(;243,46 239,53 237,60q248 37Q241 48q237 60);"/>
                    <Edge cubics="!268 0(;268,0 252,32 252,32q268 0 252 32);"/>
                    <Edge cubics="!268 0(;287,32 300,62 304,87q268 0Q293 46q304 87);"/>
                    <Edge cubics="!304 87(;308,117 308,143 304,168q304 87Q312 129q304 168);"/>
                    <Edge cubics="!366 34(;358,41 352,46 350,53q366 34Q354 46q350 53);"/>
                    <Edge cubics="!393 5(;410,69 410,122 391,163q393 5Q418 99q391 163);"/>
                    <Edge cubics="!350 53(;350,53 350,55 350,55q350 53 350 55);"/>
                    <Edge cubics="!350 55(;350,55 345,58 345,58q350 55 345 58);"/>
                    <Edge cubics="!308 83(;308,78 306,71 304,67q308 83Q308 74q304 67);"/>
                    <Edge cubics="!223 122(;223,122 220,117 220,117q223 122 220 117);"/>
                    <Edge cubics="!235 159(;235,159 235,159 235,161q235 159Q235 159q235 161);"/>
                    <Edge cubics="!235 159(;233,157 233,157 233,157q235 159Q233 157q233 157);"/>
                    <Edge cubics="!233 157(;231,150 227,143 223,138q233 157Q229 145q223 138);"/>
                    <Edge cubics="!231 104(;231,117 231,129 233,138q231 104Q231 122q233 138);"/>
                    <Edge cubics="!233 138(;233,138 223,122 223,122q233 138 223 122);"/>
                    <Edge cubics="!316 120(;316,117 316,113 314,110q316 120Q316 115q314 110);"/>
                    <Edge cubics="!235 64(;229,85 225,106 223,122q235 64Q225 94q223 122);"/>
                    <Edge cubics="!314 110(;314,101 310,92 308,83q314 110Q312 97q308 83);"/>
                    <Edge cubics="!304 67(;298,51 289,32 281,14q304 67Q293 44q281 14);"/>
                    <Edge cubics="!243 193(;243,189 243,182 239,175q243 193Q243 184q239 175);"/>
                    <Edge cubics="!243 210(;243,205 243,200 243,193q243 210Q243 203q243 193);"/>
                    <Edge cubics="!239 175(;237,168 235,166 235,161q239 175Q237 168q235 161);"/>
                    <Edge cubics="!100 233(;108,239 116,246 127,251q100 233Q108 239q127 251);"/>
                    <Edge cubics="!75 196(;75,196 91,223 91,223q75 196 91 223);"/>
                    <Edge cubics="!75 196(;75,196 77,203 77,203q75 196 77 203);"/>
                    <Edge cubics="!91 223(;91,223 95,228 95,228q91 223 95 228);"/>
                    <Edge cubics="!77 203(;83,212 87,219 91,223q77 203Q85 216q91 223);"/>
                    <Edge cubics="!56 168(;93,168 125,173 150,182q56 168Q108 168q150 182);"/>
                    <Edge cubics="!152 182(;150,182 150,182 150,182q152 182Q150 182q150 182);"/>
                    <Edge cubics="!164 186(;160,184 156,184 152,182q164 186Q158 184q152 182);"/>
                    <Edge cubics="!218 221(;202,207 185,196 164,186q218 221Q195 198q164 186);"/>
                    <Edge cubics="!548 292(;552,288 558,288 560,279q548 292Q558 288q560 279);"/>
                    <Edge cubics="!529 265(;529,265 500,251 500,251q529 265 500 251);"/>
                    <Edge cubics="!529 265(;529,265 523,260 523,260q529 265 523 260);"/>
                    <Edge cubics="!523 260(;512,256 506,251 500,251q523 260Q510 253q500 251);"/>
                    <Edge cubics="!560 279(;560,279 529,265 529,265q560 279 529 265);"/>
                    <Edge cubics="!560 279(;527,299 498,311 473,315q560 279Q512 306q473 315);"/>
                    <Edge cubics="!477 320(;481,318 487,318 493,315q477 320Q483 318q493 315);"/>
                    <Edge cubics="!450 327(;458,325 466,322 477,320q450 327Q464 325q477 320);"/>
                    <Edge cubics="!493 315(;510,311 527,302 548,292q493 315Q516 306q548 292);"/>
                    <Edge cubics="!466 451(;475,454 481,456 485,454q466 451Q481 456q485 454);"/>
                    <Edge cubics="!460 378(;454,366 448,359 439,352q460 378Q454 366q439 352);"/>
                    <Edge cubics="!475 419(;475,419 464,389 464,389q475 419 464 389);"/>
                    <Edge cubics="!475 419(;475,419 475,410 475,410q475 419 475 410);"/>
                    <Edge cubics="!475 410(;470,403 468,394 464,389q475 410Q470 398q464 389);"/>
                    <Edge cubics="!485 454(;485,454 475,419 475,419q485 454 475 419);"/>
                    <Edge cubics="!485 454(;450,442 420,431 398,414q485 454Q433 437q398 414);"/>
                    <Edge cubics="!398 421(;402,424 408,426 414,431q398 421Q406 426q414 431);"/>
                    <Edge cubics="!375 408(;383,412 389,417 398,421q375 408Q385 414q398 421);"/>
                    <Edge cubics="!414 431(;429,437 448,444 466,451q414 431Q437 440q466 451);"/>
                    <Edge cubics="!425 327(;423,325 418,322 416,318q425 327Q420 322q416 318);"/>
                    <Edge cubics="!412 327(;412,327 425,327 425,327q412 327 425 327);"/>
                    <Edge cubics="!439 352(;429,343 420,334 412,327q439 352Q425 338q412 327);"/>
                    <Edge cubics="!416 318(;433,320 454,318 473,315q416 318Q443 322q473 315);"/>
                    <Edge cubics="!464 382(;452,359 439,341 425,327q464 382Q448 350q425 327);"/>
                    <Edge cubics="!425 327(;425,327 450,327 450,327q425 327 450 327);"/>
                    <Edge cubics="!123 366(;135,366 143,364 156,361q123 366Q135 366q156 361);"/>
                    <Edge cubics="!81 359(;81,359 110,366 110,366q81 359 110 366);"/>
                    <Edge cubics="!81 359(;81,359 87,361 87,361q81 359 87 361);"/>
                    <Edge cubics="!87 361(;95,364 104,366 110,366q87 361Q100 366q110 366);"/>
                    <Edge cubics="!162 272(;162,272 152,276 152,276q162 272 152 276);"/>
                    <Edge cubics="!200 274(;189,274 183,276 173,276q200 274Q185 274q173 276);"/>
                    <Edge cubics="!127 251(;141,260 152,267 162,272q127 251Q148 262q162 272);"/>
                    <Edge cubics="!150 458(;150,465 150,472 154,477q150 458Q150 472q154 477);"/>
                    <Edge cubics="!183 458(;183,458 189,454 189,454q183 458 189 454);"/>
                    <Edge cubics="!210 440(;210,440 216,437 216,437q210 440 216 437);"/>
                    <Edge cubics="!210 440(;214,437 216,433 218,433q210 440Q216 435q218 433);"/>
                    <Edge cubics="!154 477(;154,440 160,408 168,382q154 477Q154 424q168 382);"/>
                    <Edge cubics="!160 385(;160,389 158,394 158,403q160 385Q160 391q158 403);"/>
                    <Edge cubics="!158 403(;154,417 152,437 150,458q158 403Q152 426q150 458);"/>
                    <Edge cubics="!179 355(;177,359 177,359 175,361q179 355Q177 359q175 361);"/>
                    <Edge cubics="!175 361(;173,371 168,375 168,382q175 361Q173 373q168 382);"/>
                    <Edge cubics="!116 366(;135,368 150,366 166,364q116 366Q141 368q166 364);"/>
                    <Edge cubics="!166 364(;164,371 162,378 160,385q166 364Q162 373q160 385);"/>
                    <Edge cubics="!208 313(;195,325 185,338 179,355q208 313Q191 332q179 355);"/>
                    <Edge cubics="!264 484(;264,484 285,461 285,461q264 484 285 461);"/>
                    <Edge cubics="!264 484(;264,484 270,479 270,479q264 484 270 479);"/>
                    <Edge cubics="!270 479(;277,472 283,467 285,461q270 479Q281 470q285 461);"/>
                    <Edge cubics="!243 511(;243,511 264,484 264,484q243 511 264 484);"/>
                    <Edge cubics="!231 419(;229,421 229,421 231,424q231 419Q229 421q231 424);"/>
                    <Edge cubics="!225 428(;225,428 225,431 225,431q225 428Q225 428q225 431);"/>
                    <Edge cubics="!218 433(;220,431 223,431 225,428q218 433Q223 431q225 428);"/>
                    <Edge cubics="!225 431(;225,433 225,433 225,437q225 431Q225 433q225 437);"/>
                    <Edge cubics="!216 437(;218,433 220,433 225,431q216 437Q220 433q225 431);"/>
                    <Edge cubics="!231 417(;231,417 231,417 231,419q231 417Q231 417q231 419);"/>
                    <Edge cubics="!285 461(;285,461 287,461 287,461q285 461 287 461);"/>
                    <Edge cubics="!287 461(;287,461 289,458 289,458q287 461 289 458);"/>
                    <Edge cubics="!302 435(;302,435 302,435 302,437q302 435Q302 435q302 437);"/>
                    <Edge cubics="!298 440(;298,440 298,442 298,442q298 440Q298 440q298 442);"/>
                    <Edge cubics="!291 451(;293,449 293,444 298,440q291 451Q293 447q298 440);"/>
                    <Edge cubics="!300 433(;300,433 300,433 302,435q300 433Q300 433q302 435);"/>
                    <Edge cubics="!373 405(;373,403 373,398 370,394q373 405Q373 398q370 394);"/>
                    <Edge cubics="!373 405(;373,405 375,408 375,408q373 405 375 408);"/>
                    <Edge cubics="!373 440(;373,428 373,417 373,405q373 440Q375 421q373 405);"/>
                    <Edge cubics="!370 394(;379,403 387,410 398,414q370 394Q383 405q398 414);"/>
                    <Edge cubics="!298 442(;302,447 304,451 308,456q298 442Q302 449q308 456);"/>
                    <Edge cubics="!314 357(;308,359 300,359 291,359q314 357Q304 359q291 359);"/>
                    <Edge cubics="!350 336(;339,345 329,352 314,357q350 336Q333 350q314 357);"/>
                    <Edge cubics="!291 196(;291,196 293,196 293,196q291 196 293 196);"/>
                    <Edge cubics="!308 198(;310,196 310,196 314,193q308 198Q310 196q314 193);"/>
                    <Edge cubics="!304 168(;302,177 298,189 293,196q304 168Q300 182q293 196);"/>
                    <Edge cubics="!293 196(;298,196 304,198 308,198q293 196Q302 196q308 198);"/>
                    <Edge cubics="!227 230(;225,228 223,223 218,221q227 230Q223 226q218 221);"/>
                    <Edge cubics="!235 221(;239,216 243,214 243,212q235 221Q241 214q243 212);"/>
                    <Edge cubics="!243 212(;243,212 243,210 243,210q243 212Q243 212q243 210);"/>
                    <Edge cubics="!227 230(;231,228 233,223 235,221q227 230Q231 226q235 221);"/>
                    <Edge cubics="!216 306(;214,297 212,288 212,279q216 306Q212 292q212 279);"/>
                    <Edge cubics="!212 279(;212,276 212,276 212,274q212 279Q212 276q212 274);"/>
                    <Edge cubics="!212 274(;212,258 218,242 227,230q212 274Q214 249q227 230);"/>
                    <Edge cubics="!243 212(;258,203 275,196 291,196q243 212Q266 196q291 196);"/>
                    <Edge cubics="!281 359(;277,359 273,357 270,357q281 359Q275 357q270 357);"/>
                    <Edge cubics="!291 359(;289,359 283,359 281,359q291 359Q285 359q281 359);"/>
                    <Edge cubics="!248 345(;243,343 239,338 235,336q248 345Q241 341q235 336);"/>
                    <Edge cubics="!270 357(;262,355 256,350 248,345q270 357Q258 352q248 345);"/>
                    <Edge cubics="!248 345(;237,366 233,389 231,417q248 345Q233 378q231 417);"/>
                    <Edge cubics="!235 336(;225,327 220,315 216,306q235 336Q223 320q216 306);"/>
                    <Edge cubics="!216 306(;214,309 210,311 208,313q216 306Q212 309q208 313);"/>
                    <Edge cubics="!212 274(;208,274 202,274 200,274q212 274Q206 274q200 274);"/>
                    <Edge cubics="!348 221(;348,221 348,221 350,221q348 221Q348 221q350 221);"/>
                    <Edge cubics="!325 205(;333,207 341,214 348,221q325 205Q337 210q348 221);"/>
                    <Edge cubics="!354 226(;354,228 356,228 356,228q354 226Q354 228q356 228);"/>
                    <Edge cubics="!356 223(;356,226 356,228 356,228q356 223Q356 226q356 228);"/>
                    <Edge cubics="!354 226(;354,226 356,223 356,223q354 226 356 223);"/>
                    <Edge cubics="!350 221(;350,223 352,223 354,226q350 221Q352 223q354 226);"/>
                    <Edge cubics="!373 279(;373,283 373,288 370,292q373 279Q373 286q370 292);"/>
                    <Edge cubics="!368 249(;370,258 373,267 373,279q368 249Q373 262q373 279);"/>
                    <Edge cubics="!435 237(;410,235 387,239 368,249q435 237Q398 233q368 249);"/>
                    <Edge cubics="!350 334(;350,334 350,334 350,336q350 334Q350 334q350 336);"/>
                    <Edge cubics="!370 292(;368,309 360,320 350,334q370 292Q368 315q350 334);"/>
                    <Edge cubics="!95 228(;95,228 95,230 98,230q95 228Q95 230q98 230);"/>
                    <Edge cubics="!98 230(;98,233 98,233 100,233q98 230Q98 233q100 233);"/>
                    <Edge cubics="!156 361(;160,359 164,359 168,359q156 361Q160 359q168 359);"/>
                    <Edge cubics="!168 359(;166,359 166,361 166,364q168 359Q166 361q166 364);"/>
                    <Edge cubics="!116 366(;118,366 120,366 123,366q116 366Q118 366q123 366);"/>
                    <Edge cubics="!110 366(;110,366 116,366 116,366q110 366 116 366);"/>
                    <Edge cubics="!291 454(;291,454 291,451 291,451q291 454Q291 454q291 451);"/>
                    <Edge cubics="!291 456(;293,451 295,447 298,442q291 456Q293 449q298 442);"/>
                    <Edge cubics="!289 458(;289,456 289,456 291,454q289 458Q289 456q291 454);"/>
                    <Edge cubics="!289 458(;289,456 289,456 291,456q289 458Q289 456q291 456);"/>
                    <Edge cubics="!464 385(;464,382 460,380 460,378q464 385Q462 382q460 378);"/>
                    <Edge cubics="!464 385(;464,385 464,382 464,382q464 385 464 382);"/>
                    <Edge cubics="!464 389(;464,389 464,385 464,385q464 389 464 385);"/>
                    <Edge cubics="!500 251(;500,251 495,246 495,246q500 251 495 246);"/>
                    <Edge cubics="!500 251(;495,249 493,246 489,246q500 251Q493 246q489 246);"/>
                    <Edge cubics="!100 233(;116,251 133,265 152,276q100 233Q125 260q152 276);"/>
                    <Edge cubics="!345 58(;345,58 345,60 343,60q345 58Q345 58q343 60);"/>
                    <Edge cubics="!343 60(;343,62 343,62 343,62q343 60Q343 62q343 62);"/>
                    <Edge cubics="!343 62(;331,83 323,101 316,120q343 62Q325 92q316 120);"/>
                    <Edge cubics="!289 410(;293,417 298,426 300,433q289 410Q293 421q300 433);"/>
                    <Edge cubics="!320 474(;320,474 320,518 320,518q320 474 320 518);"/>
                    <Edge cubics="!358 509(;360,509 360,509 362,507q358 509Q360 509q362 507);"/>
                    <Edge cubics="!352 511(;352,511 354,511 354,511q352 511 354 511);"/>
                    <Edge cubics="!354 511(;356,511 356,511 358,511q354 511Q356 511q358 511);"/>
                    <Edge cubics="!358 511(;358,511 358,509 358,509q358 511 358 509);"/>
                    <Edge cubics="!356 509(;356,509 356,509 358,511q356 509Q356 509q358 511);"/>
                    <Edge cubics="!343 500(;345,507 350,509 354,511q343 500Q350 507q354 511);"/>
                    <Edge cubics="!308 456(;310,461 314,467 320,474q308 456Q312 465q320 474);"/>
                    <Edge cubics="!302 437(;308,447 312,458 320,467q302 437Q308 454q320 467);"/>
                    <Edge cubics="!289 557(;289,557 289,458 289,458q289 557 289 458);"/>
                    <Edge cubics="!281 359(;281,375 285,394 289,410q281 359Q281 385q289 410);"/>
                    <Edge cubics="!268 233(;268,233 258,239 258,239q268 233 258 239);"/>
                    <Edge cubics="!237 256(;241,258 245,258 250,260q237 256Q243 258q250 260);"/>
                    <Edge cubics="!256 550(;252,550 250,550 248,550q256 550Q252 550q248 550);"/>
                    <Edge cubics="!285 580(;285,578 285,578 285,578q285 580Q285 578q285 578);"/>
                    <Edge cubics="!268 592(;270,589 270,589 273,589q268 592Q270 589q273 589);"/>
                    <Edge cubics="!273 589(;273,587 275,587 275,587q273 589Q273 587q275 587);"/>
                    <Edge cubics="!264 553(;262,546 256,546 248,550q264 553Q260 543q248 550);"/>
                    <Edge cubics="!260 596(;262,596 264,594 268,592q260 596Q264 594q268 592);"/>
                    <Edge cubics="!248 550(;227,546 202,543 173,541q248 550Q218 543q173 541);"/>
                    <Edge cubics="!333 228(;333,228 333,239 333,239q333 228 333 239);"/>
                    <Edge cubics="!316 262(;316,262 323,262 323,262q316 262 323 262);"/>
                    <Edge cubics="!323 262(;323,262 329,262 329,262q323 262 329 262);"/>
                    <Edge cubics="!300 256(;300,256 289,256 289,256q300 256 289 256);"/>
                    <Edge cubics="!327 311(;327,311 314,315 314,315q327 311 314 315);"/>
                    <Edge cubics="!291 283(;295,288 298,290 302,292q291 283Q298 288q302 292);"/>
                    <Edge cubics="!316 244(;316,244 316,262 316,262q316 244 316 262);"/>
                    <Edge cubics="!320 518(;320,520 320,523 323,525q320 518Q320 523q323 525);"/>
                    <Edge cubics="!323 525(;323,525 320,525 320,525q323 525 320 525);"/>
                    <Edge cubics="!362 555(;370,555 381,557 391,557q362 555Q375 557q391 557);"/>
                    <Edge cubics="!373 537(;373,537 391,557 391,557q373 537 391 557);"/>
                    <Edge cubics="!360 555(;358,553 354,550 352,548q360 555Q356 553q352 548);"/>
                    <Edge cubics="!362 555(;360,555 360,555 360,555q362 555Q360 555q360 555);"/>
                    <Edge cubics="!325 530(;327,534 333,541 341,546q325 530Q329 539q341 546);"/>
                    <Edge cubics="!335 537(;333,534 329,532 325,530q335 537Q331 532q325 530);"/>
                    <Edge cubics="!302 569(;302,569 289,557 289,557q302 569 289 557);"/>
                    <Edge cubics="!341 546(;345,548 352,553 360,555q341 546Q350 550q360 555);"/>
                    <Edge cubics="!391 557(;391,557 410,578 410,578q391 557 410 578);"/>
                    <Edge cubics="!323 525(;323,527 323,530 325,530q323 525Q323 527q325 530);"/>
                    <Edge cubics="!373 537(;373,537 323,525 323,525q373 537 323 525);"/>
                    <Edge cubics="!289 557(;289,557 285,555 285,555q289 557 285 555);"/>
                    <Edge cubics="!287 555(;287,555 285,555 285,555q287 555Q285 555q285 555);"/>
                    <Edge cubics="!304 327(;304,327 275,327 275,327q304 327 275 327);"/>
                    <Edge cubics="!281 279(;281,279 291,283 291,283q281 279 291 283);"/>
                    <Edge cubics="!320 117(;323,115 323,108 325,104q320 117Q323 108q325 104);"/>
                    <Edge cubics="!325 104(;325,99 329,94 331,90q325 104Q329 94q331 90);"/>
                    <Edge cubics="!331 90(;331,87 333,85 333,83q331 90 333 83);"/>
                    <Edge cubics="!345 67(;345,64 348,62 350,62q345 67 350 62);"/>
                    <Edge cubics="!350 62(;350,58 352,58 356,53q350 62 356 53);"/>
                    <Edge cubics="!356 53(;356,51 358,48 358,46q356 53 358 46);"/>
                    <Edge cubics="!385 14(;385,14 387,14 387,14q385 14 387 14);"/>
                    <Edge cubics="!387 14(;391,21 391,32 385,41q387 14Q398 28q385 41);"/>
                    <Edge cubics="!333 113(;333,117 331,120 329,122q333 113 329 122);"/>
                    <Edge cubics="!329 122(;329,127 329,129 329,131q329 122 329 131);"/>
                    <Edge cubics="!329 131(;327,136 327,138 323,140q329 131Q327 138q323 140);"/>
                    <Edge cubics="!323 140(;325,145 325,154 323,161q323 140Q325 152q323 161);"/>
                    <Edge cubics="!323 161(;323,163 320,166 320,168q323 161 320 168);"/>
                    <Edge cubics="!320 168(;320,173 323,175 323,177q320 168 323 177);"/>
                    <Edge cubics="!310 175(;310,166 310,161 314,154q310 175Q310 161q314 154);"/>
                    <Edge cubics="!370 193(;373,191 375,189 375,184q370 193 375 184);"/>
                    <Edge cubics="!375 184(;379,180 383,173 387,168q375 184 387 168);"/>
                    <Edge cubics="!360 431(;362,410 360,387 352,364q360 431Q364 396q352 364);"/>
                    <Edge cubics="!352 364(;350,359 350,350 356,345q352 364Q350 350q356 345);"/>
                    <Edge cubics="!358 46(;358,46 385,14 385,14q358 46 385 14);"/>
                    <Edge cubics="!333 83(;335,81 335,81 335,81q333 83Q335 81q335 81);"/>
                    <Edge cubics="!343 62(;341,67 339,71 335,81q343 62Q339 69q335 81);"/>
                    <Edge cubics="!335 81(;339,74 343,69 345,67q335 81Q341 71q345 67);"/>
                    <Edge cubics="!385 41(;385,41 366,62 366,62q385 41 366 62);"/>
                    <Edge cubics="!366 62(;366,62 333,113 333,113q366 62 333 113);"/>
                    <Edge cubics="!318 124(;316,124 316,122 316,120q318 124Q316 122q316 120);"/>
                    <Edge cubics="!316 129(;316,129 318,124 318,124q316 129 318 124);"/>
                    <Edge cubics="!318 124(;318,124 320,117 320,117q318 124 320 117);"/>
                    <Edge cubics="!314 154(;314,154 316,129 316,129q314 154 316 129);"/>
                    <Edge cubics="!323 203(;320,205 320,205 320,205q323 203Q320 205q320 205);"/>
                    <Edge cubics="!325 196(;323,198 323,200 323,203q325 196Q323 198q323 203);"/>
                    <Edge cubics="!325 196(;325,196 325,205 325,205q325 196 325 205);"/>
                    <Edge cubics="!323 203(;323,203 325,203 325,205q323 203Q323 203q325 205);"/>
                    <Edge cubics="!316 200(;316,200 316,200 316,198q316 200Q316 200q316 198);"/>
                    <Edge cubics="!320 205(;318,205 316,203 316,200q320 205Q316 203q316 200);"/>
                    <Edge cubics="!316 198(;314,196 314,193 314,193q316 198Q314 196q314 193);"/>
                    <Edge cubics="!308 198(;312,200 314,200 316,200q308 198Q314 200q316 200);"/>
                    <Edge cubics="!364 205(;366,203 368,198 370,193q364 205Q366 200q370 193);"/>
                    <Edge cubics="!364 207(;364,207 364,207 364,205q364 207Q364 207q364 205);"/>
                    <Edge cubics="!362 210(;362,210 364,207 364,207q362 210 364 207);"/>
                    <Edge cubics="!356 228(;356,228 358,230 358,230q356 228 358 230);"/>
                    <Edge cubics="!358 233(;358,233 358,230 358,230q358 233 358 230);"/>
                    <Edge cubics="!362 237(;360,237 358,235 358,233q362 237Q358 237q358 233);"/>
                    <Edge cubics="!362 237(;364,239 366,244 368,249q362 237Q366 242q368 249);"/>
                    <Edge cubics="!323 177(;325,184 325,191 325,196q323 177Q325 186q325 196);"/>
                    <Edge cubics="!314 193(;312,189 310,182 310,175q314 193Q310 184q310 175);"/>
                    <Edge cubics="!368 401(;368,405 368,408 368,410q368 401Q368 405q368 410);"/>
                    <Edge cubics="!368 391(;368,394 368,398 368,401q368 391Q368 396q368 401);"/>
                    <Edge cubics="!368 401(;368,401 373,405 373,405q368 401 373 405);"/>
                    <Edge cubics="!373 433(;373,428 370,421 368,410q373 433Q373 426q368 410);"/>
                    <Edge cubics="!366 472(;364,479 364,484 364,488q366 472Q364 481q364 488);"/>
                    <Edge cubics="!366 472(;366,472 366,470 366,470q366 472 366 470);"/>
                    <Edge cubics="!358 509(;358,509 360,497 360,497q358 509 360 497);"/>
                    <Edge cubics="!360 497(;360,497 358,500 356,500q360 497Q358 500q356 500);"/>
                    <Edge cubics="!364 488(;362,493 362,495 360,497q364 488Q362 493q360 497);"/>
                    <Edge cubics="!366 472(;366,472 370,447 370,447q366 472 370 447);"/>
                    <Edge cubics="!168 394(;170,391 173,387 175,385q168 394 175 385);"/>
                    <Edge cubics="!175 385(;175,380 177,375 179,371q175 385 179 371);"/>
                    <Edge cubics="!206 322(;206,322 206,322 208,320q206 322 208 320);"/>
                    <Edge cubics="!208 320(;210,327 212,334 210,341q208 320Q212 334q210 341);"/>
                    <Edge cubics="!210 341(;208,345 206,348 204,352q210 341 204 352);"/>
                    <Edge cubics="!193 366(;193,368 193,371 193,373q193 366 193 373);"/>
                    <Edge cubics="!193 373(;193,375 191,380 189,382q193 373Q193 378q189 382);"/>
                    <Edge cubics="!175 419(;175,421 173,424 173,426q175 419 173 426);"/>
                    <Edge cubics="!173 426(;173,433 168,435 168,442q173 426Q173 433q168 442);"/>
                    <Edge cubics="!168 442(;166,444 168,447 166,451q168 442 166 451);"/>
                    <Edge cubics="!164 474(;162,474 160,474 160,474q164 474 160 474);"/>
                    <Edge cubics="!160 474(;158,470 158,465 158,461q160 474Q158 470q158 461);"/>
                    <Edge cubics="!212 230(;212,233 210,235 208,235q212 230Q212 235q208 235);"/>
                    <Edge cubics="!208 235(;208,235 206,235 206,235q208 235 206 235);"/>
                    <Edge cubics="!206 235(;202,233 198,233 195,230q206 235Q198 233q195 230);"/>
                    <Edge cubics="!195 230(;191,228 189,223 183,223q195 230Q187 223q183 223);"/>
                    <Edge cubics="!183 223(;183,223 183,223 183,221q183 223 183 221);"/>
                    <Edge cubics="!183 221(;181,221 177,221 175,219q183 221Q177 221q175 219);"/>
                    <Edge cubics="!175 219(;173,216 170,214 168,214q175 219 168 214);"/>
                    <Edge cubics="!168 214(;166,214 164,214 162,214q168 214 162 214);"/>
                    <Edge cubics="!162 214(;160,214 160,212 160,212q162 214 160 212);"/>
                    <Edge cubics="!160 212(;158,210 152,210 150,210q160 212Q158 210q150 210);"/>
                    <Edge cubics="!150 210(;150,207 150,207 148,205q150 210 148 205);"/>
                    <Edge cubics="!148 205(;143,205 139,205 135,203q148 205 135 203);"/>
                    <Edge cubics="!135 203(;135,200 133,200 131,200q135 203Q135 200q131 200);"/>
                    <Edge cubics="!131 200(;123,200 114,198 106,198q131 200 106 198);"/>
                    <Edge cubics="!106 198(;106,196 106,196 106,196q106 198 106 196);"/>
                    <Edge cubics="!60 170(;75,170 91,170 106,173q60 170Q85 168q106 173);"/>
                    <Edge cubics="!106 173(;108,173 110,173 108,175q106 173Q110 173q108 175);"/>
                    <Edge cubics="!108 175(;116,175 123,177 131,177q108 175 131 177);"/>
                    <Edge cubics="!131 177(;135,180 141,182 148,182q131 177Q141 182q148 182);"/>
                    <Edge cubics="!148 182(;150,184 152,184 152,186q148 182Q152 186q152 186);"/>
                    <Edge cubics="!152 186(;154,186 158,186 160,189q152 186Q156 184q160 189);"/>
                    <Edge cubics="!173 193(;177,193 179,198 183,200q173 193Q177 193q183 200);"/>
                    <Edge cubics="!183 200(;183,200 185,200 185,200q183 200 185 200);"/>
                    <Edge cubics="!185 200(;187,200 189,203 187,203q185 200Q189 203q187 203);"/>
                    <Edge cubics="!187 203(;191,203 195,205 198,210q187 203Q193 203q198 210);"/>
                    <Edge cubics="!198 210(;202,210 206,212 210,214q198 210Q206 210q210 214);"/>
                    <Edge cubics="!210 214(;212,219 214,226 212,230q210 214Q214 223q212 230);"/>
                    <Edge cubics="!518 262(;523,265 529,267 533,274q518 262Q529 267q533 274);"/>
                    <Edge cubics="!533 274(;535,279 535,288 531,290q533 274Q539 286q531 290);"/>
                    <Edge cubics="!531 290(;525,290 518,288 512,286q531 290Q527 290q512 286);"/>
                    <Edge cubics="!512 286(;508,283 506,281 502,279q512 286 502 279);"/>
                    <Edge cubics="!502 279(;485,269 468,262 452,260q502 279Q468 262q452 260);"/>
                    <Edge cubics="!452 260(;431,258 410,265 391,262q452 260Q439 258q420 262Q400 262q391 262);"/>
                    <Edge cubics="!391 262(;387,258 385,249 391,244q391 262Q385 251q391 244);"/>
                    <Edge cubics="!391 244(;391,242 398,239 402,239q391 244Q393 239q402 239);"/>
                    <Edge cubics="!195 281(;200,288 200,295 195,302q195 281Q202 290q195 302);"/>
                    <Edge cubics="!195 302(;191,302 185,302 179,302q195 302Q179 302q179 302);"/>
                    <Edge cubics="!179 302(;177,302 175,299 173,299q179 302 173 299);"/>
                    <Edge cubics="!102 318(;100,318 98,320 98,322q102 318 98 322);"/>
                    <Edge cubics="!91 327(;87,327 85,329 83,332q91 327Q87 327q83 332);"/>
                    <Edge cubics="!83 332(;81,334 81,334 79,334q83 332 79 334);"/>
                    <Edge cubics="!60 175(;60,173 60,173 60,170q60 175Q60 173q60 170);"/>
                    <Edge cubics="!73 193(;73,193 60,191 60,191q73 193 60 191);"/>
                    <Edge cubics="!73 193(;73,193 75,196 75,196q73 193 75 196);"/>
                    <Edge cubics="!106 196(;106,196 73,193 73,193q106 196 73 193);"/>
                    <Edge cubics="!145 276(;145,276 168,279 168,279q145 276 168 279);"/>
                    <Edge cubics="!152 276(;152,276 145,276 145,276q152 276 145 276);"/>
                    <Edge cubics="!116 286(;116,286 135,281 135,281q116 286 135 281);"/>
                    <Edge cubics="!135 281(;135,281 145,276 145,276q135 281 145 276);"/>
                    <Edge cubics="!98 322(;98,322 91,327 91,327q98 322 91 327);"/>
                    <Edge cubics="!173 279(;173,279 195,281 195,281q173 279 195 281);"/>
                    <Edge cubics="!179 371(;179,371 206,322 206,322q179 371 206 322);"/>
                    <Edge cubics="!173 299(;173,299 150,299 150,299q173 299 150 299);"/>
                    <Edge cubics="!173 276(;173,276 168,276 168,279q173 276Q170 276q168 279);"/>
                    <Edge cubics="!168 279(;168,279 173,279 173,279q168 279 173 279);"/>
                    <Edge cubics="!54 341(;48,345 45,350 45,352q54 341Q45 348q45 352);"/>
                    <Edge cubics="!54 345(;52,348 50,350 45,352q54 345Q50 348q45 352);"/>
                    <Edge cubics="!54 355(;54,355 54,345 54,345q54 355 54 345);"/>
                    <Edge cubics="!54 345(;54,345 54,341 54,341q54 345 54 341);"/>
                    <Edge cubics="!54 341(;54,341 52,338 52,338q54 341 52 338);"/>
                    <Edge cubics="!233 488(;233,490 233,493 233,495q233 488Q233 490q233 495);"/>
                    <Edge cubics="!225 437(;225,451 229,470 233,488q225 437Q227 458q233 488);"/>
                    <Edge cubics="!231 424(;229,444 231,465 237,488q231 424Q229 454q237 488);"/>
                    <Edge cubics="!160 426(;160,426 168,394 168,394q160 426 168 394);"/>
                    <Edge cubics="!166 461(;168,463 168,465 166,467q166 461Q168 465q166 467);"/>
                    <Edge cubics="!154 477(;154,477 160,474 160,474q154 477 160 474);"/>
                    <Edge cubics="!166 467(;166,470 164,472 164,474q166 467Q166 472q164 474);"/>
                    <Edge cubics="!158 461(;158,461 160,426 160,426q158 461 160 426);"/>
                    <Edge cubics="!166 467(;166,467 183,458 183,458q166 467 183 458);"/>
                    <Edge cubics="!189 382(;189,382 175,419 175,419q189 382 175 419);"/>
                    <Edge cubics="!56 168(;56,168 60,175 60,175q56 168 60 175);"/>
                    <Edge cubics="!60 191(;58,186 58,180 60,175q60 191Q56 182q60 175);"/>
                    <Edge cubics="!448 237(;448,237 445,237 443,237q448 237Q448 237q443 237);"/>
                    <Edge cubics="!443 237(;441,237 439,237 435,237q443 237Q441 237q435 237);"/>
                    <Edge cubics="!402 239(;414,237 427,237 435,237q402 239Q420 237q435 237);"/>
                    <Edge cubics="!489 246(;485,244 483,244 479,244q489 246Q485 244q479 244);"/>
                    <Edge cubics="!458 239(;456,237 452,237 448,237q458 239Q454 237q448 237);"/>
                    <Edge cubics="!473 500(;485,502 498,507 512,511q473 500Q491 502q512 511);"/>
                    <Edge cubics="!333 488(;335,493 339,497 343,500q333 488Q337 495q343 500);"/>
                    <Edge cubics="!320 467(;327,474 331,481 337,488q320 467Q329 479q337 488);"/>
                    <Edge cubics="!320 474(;325,479 329,484 333,488q320 474Q327 481q333 488);"/>
                    <Edge cubics="!356 488(;356,481 356,474 356,465q356 488Q356 479q356 465);"/>
                    <Edge cubics="!356 500(;356,497 356,493 356,488q356 500Q356 495q356 488);"/>
                    <Edge cubics="!356 465(;358,451 360,437 360,431q356 465Q360 442q360 431);"/>
                    <Edge cubics="!337 488(;343,495 350,502 356,509q337 488Q345 500q356 509);"/>
                    <Edge cubics="!479 244(;491,249 502,253 518,262q479 244Q495 251q518 262);"/>
                    <Edge cubics="!512 511(;520,513 531,518 539,523q512 511Q525 516q539 523);"/>
                    <Edge cubics="!160 189(;160,189 173,193 173,193q160 189 173 193);"/>
                    <Edge cubics="!204 352(;204,352 193,366 193,366q204 352 193 366);"/>
                    <Edge cubics="!287 578(;287,578 285,578 285,578q287 578 285 578);"/>
                    <Edge cubics="!458 239(;462,239 466,239 470,239q458 239Q464 239q470 239);"/>
                    <Edge cubics="!470 239(;473,242 477,242 479,244q470 239Q475 242q479 244);"/>
                    <Edge cubics="!362 210(;360,214 358,219 356,223q362 210Q358 216q356 223);"/>
                    <Edge cubics="!348 221(;352,216 358,214 362,210q348 221Q356 214q362 210);"/>
                    <Edge cubics="!495 246(;485,244 477,242 470,239q495 246Q481 244q470 239);"/>
                    <Edge cubics="!302 569(;302,569 287,578 287,578q302 569 287 578);"/>
                    <Edge cubics="!287 578(;287,578 287,578 289,578q287 578Q287 578q289 578);"/>
                    <Edge cubics="!235 64(;235,67 235,67 235,69q235 64Q235 67q235 69);"/>
                    <Edge cubics="!56 355(;56,355 54,355 54,355q56 355 54 355);"/>
                    <Edge cubics="!56 355(;56,355 81,359 81,359q56 355 81 359);"/>
                    <Edge cubics="!64 348(;62,350 58,352 56,355q64 348Q60 352q56 355);"/>
                    <Edge cubics="!150 299(;150,299 102,318 102,318q150 299 102 318);"/>
                    <Edge cubics="!85 304(;85,304 116,286 116,286q85 304 116 286);"/>
                    <Edge cubics="!58 327(;58,327 85,304 85,304q58 327 85 304);"/>
                    <Edge cubics="!245 239(;245,239 237,256 237,256q245 239 237 256);"/>
                    <Edge cubics="!183 458(;183,458 193,454 193,454q183 458 193 454);"/>
                    <Edge cubics="!189 454(;191,454 191,454 193,454q189 454Q191 454q193 454);"/>
                    <Edge cubics="!193 454(;193,454 210,440 210,440q193 454 210 440);"/>
                    <Edge cubics="!166 451(;166,451 166,461 166,461q166 451 166 461);"/>
                    <Edge cubics="!45 352(;45,352 54,355 54,355q45 352 54 355);"/>
                    <Edge cubics="!393 5(;393,5 385,14 385,14q393 5 385 14);"/>
                    <Edge cubics="!385 14(;385,14 366,34 366,34q385 14 366 34);"/>
                    <Edge cubics="!391 163(;389,166 389,166 387,168q391 163Q389 166q387 168);"/>
                    <Edge cubics="!337 251(;337,253 335,258 329,265q337 251Q337 256q329 265);"/>
                    <Edge cubics="!329 265(;331,269 331,274 331,279q329 265Q331 272q331 279);"/>
                    <Edge cubics="!329 262(;329,262 329,265 329,265q329 262 329 265);"/>
                    <Edge cubics="!312 262(;314,262 314,262 316,262q312 262Q314 262q316 262);"/>
                    <Edge cubics="!300 256(;304,258 308,260 312,262q300 256Q306 260q312 262);"/>
                    <Edge cubics="!302 292(;302,292 293,315 293,315q302 292 293 315);"/>
                    <Edge cubics="!356 345(;354,341 352,336 350,334q356 345Q354 338q350 334);"/>
                    <Edge cubics="!358 348(;360,352 364,359 366,368q358 348Q362 355q366 368);"/>
                    <Edge cubics="!356 345(;356,345 356,345 358,348q356 345Q356 345q358 348);"/>
                    <Edge cubics="!323 262(;318,267 314,267 312,262q323 262Q316 269q312 262);"/>
                    <Edge cubics="!406 311(;395,304 383,297 370,292q406 311Q389 299q370 292);"/>
                    <Edge cubics="!416 318(;414,315 410,313 406,311q416 318Q412 313q406 311);"/>
                    <Edge cubics="!375 184(;370,191 366,198 364,205q375 184Q368 193q364 205);"/>
                    <Edge cubics="!437 502(;437,502 437,500 437,500q437 502 437 500);"/>
                    <Edge cubics="!416 513(;416,513 437,502 437,502q416 513 437 502);"/>
                    <Edge cubics="!325 530(;325,530 320,530 320,530q325 530 320 530);"/>
                    <Edge cubics="!368 410(;368,431 368,451 366,470q368 410Q368 442q366 470);"/>
                    <Edge cubics="!452 553(;452,553 429,548 429,548q452 553 429 548);"/>
                    <Edge cubics="!366 507(;383,504 406,502 437,502q366 507Q391 502q437 502);"/>
                    <Edge cubics="!41 594(;39,596 35,601 31,603q41 594Q37 599q31 603);"/>
                    <Edge cubics="!449 500(;449,500 473,500 473,500q449 500 473 500);"/>
                    <Edge cubics="!437 500(;437,500 449,500 449,500q437 500 449 500);"/>
                    <Edge cubics="!437 502(;441,501 445,500 449,500q437 502Q443 500q449 500);"/>
                    <Edge cubics="!366 368(;366,370 366,372 367,374q366 368Q366 371q367 374);"/>
                    <Edge cubics="!370 393(;370,393 370,393 370,394q370 393Q370 393q370 394);"/>
                    <Edge cubics="!368 391(;369,391 369,392 370,393q368 391Q369 391q370 393);"/>
                    <Edge cubics="!370 447(;370,447 371,446 371,446q370 447 371 446);"/>
                    <Edge cubics="!371 446(;371,446 373,440 373,440q371 446 373 440);"/>
                    <Edge cubics="!371 446(;372,441 373,437 373,433q371 446Q373 439q373 433);"/>
                    <Edge cubics="!52 338(;52,338 58,327 58,327q52 338 58 327);"/>
                    <Edge cubics="!79 334(;79,334 64,348 64,348q79 334 64 348);"/>
                    <Edge cubics="!285 555(;283,555 281,555 280,555q285 555Q282 555q280 555);"/>
                    <Edge cubics="!239 508(;240,509 242,510 243,511q239 508Q241 510q243 511);"/>
                    <Edge cubics="!242 508(;242,509 242,510 243,511q242 508Q242 510q243 511);"/>
                    <Edge cubics="!280 583(;281,582 283,581 285,580q280 583Q282 581q285 580);"/>
                    <Edge cubics="!280 555(;275,555 271,555 268,555q280 555Q273 555q268 555);"/>
                    <Edge cubics="!275 587(;276,586 278,584 280,583q275 587Q277 585q280 583);"/>
                    <Edge cubics="!237 488(;238,495 240,501 242,508q237 488Q239 498q242 508);"/>
                    <Edge cubics="!233 495(;234,501 236,505 239,508q233 495Q234 504q239 508);"/>
                    <Edge cubics="!49 653(;49,653 45,656 45,656q49 653 45 656);"/>
                    <Edge cubics="!248 578(;248,578 302,569 302,569q248 578 302 569);"/>
                    <Edge cubics="!285 555(;285,555 264,553 264,553q285 555 264 553);"/>
                    <Edge cubics="!61 650(;61,651 60,652 60,653q61 650 60 653);"/>
                    <Edge cubics="!38 652(;36,651 35,648 33,647q38 652 33 647);"/>
                    <Edge cubics="!40 628(;45,629 51,631 56,633q40 628 56 633);"/>
                    <Edge cubics="!56 633(;58,634 60,636 62,638q56 633 62 638);"/>
                    <Edge cubics="!58 602(;58,606 56,610 53,613q58 602Q58 608q53 613);"/>
                    <Edge cubics="!43 601(;45,599 47,595 49,596q43 601Q48 596q49 596);"/>
                    <Edge cubics="!49 596(;50,595 50,594 50,594q49 596 50 594);"/>
                    <Edge cubics="!16 616(;17,616 18,616 19,617q16 616Q17 616q19 617);"/>
                    <Edge cubics="!10 635(;9,633 8,631 7,630q10 635Q8 632q7 630);"/>
                    <Edge cubics="!0 627(;0,627 10,635 10,635q0 627 10 635);"/>
                    <Edge cubics="!0 627(;3,628 5,629 7,630q0 627Q4 628q7 630);"/>
                    <Edge cubics="!23 644(;22,643 21,643 20,643q23 644Q21 643q20 643);"/>
                    <Edge cubics="!10 635(;10,635 20,643 20,643q10 635 20 643);"/>
                    <Edge cubics="!7 630(;6,628 6,626 6,624q7 630Q6 627q6 624);"/>
                    <Edge cubics="!49 596(;49,596 41,594 41,594q49 596 41 594);"/>
                    <Edge cubics="!39 603(;41,602 42,602 43,601q39 603Q42 602q43 601);"/>
                    <Edge cubics="!31 603(;31,603 31,604 31,604q31 603 31 604);"/>
                    <Edge cubics="!31 604(;30,605 28,606 27,607q31 604Q29 605q27 607);"/>
                    <Edge cubics="!26 608(;26,607 26,607 27,607q26 608Q26 607q27 607);"/>
                    <Edge cubics="!31 604(;31,604 32,603 32,603q31 604 32 603);"/>
                    <Edge cubics="!43 622(;42,622 40,622 39,623q43 622Q41 622q39 623);"/>
                    <Edge cubics="!32 603(;35,603 37,603 39,603q32 603Q36 603q39 603);"/>
                    <Edge cubics="!39 603(;37,602 34,602 31,603q39 603Q36 602q31 603);"/>
                    <Edge cubics="!57 599(;58,600 58,601 58,602q57 599Q58 600q58 602);"/>
                    <Edge cubics="!50 594(;53,593 56,595 57,599q50 594Q55 593q57 599);"/>
                    <Edge cubics="!53 613(;51,616 48,619 43,622q53 613Q50 618q43 622);"/>
                    <Edge cubics="!43 622(;43,622 98,610 98,610q43 622 98 610);"/>
                    <Edge cubics="!98 610(;98,610 57,599 57,599q98 610 57 599);"/>
                    <Edge cubics="!62 638(;62,639 62,640 63,641q62 638Q62 639q63 641);"/>
                    <Edge cubics="!63 641(;62,643 62,646 61,650q63 641Q62 644q61 650);"/>
                    <Edge cubics="!31 646(;30,645 30,645 29,645q31 646Q30 645q29 645);"/>
                    <Edge cubics="!33 647(;32,646 32,646 31,646q33 647Q32 646q31 646);"/>
                    <Edge cubics="!31 652(;31,652 31,646 31,646q31 652 31 646);"/>
                    <Edge cubics="!31 652(;30,649 30,647 29,645q31 652Q30 648q29 645);"/>
                    <Edge cubics="!42 653(;42,653 39,652 39,652q42 653 39 652);"/>
                    <Edge cubics="!39 652(;39,652 38,652 38,652q39 652 38 652);"/>
                    <Edge cubics="!34 626(;36,627 38,627 40,628q34 626Q37 627q40 628);"/>
                    <Edge cubics="!31 652(;31,652 38,652 38,652q31 652 38 652);"/>
                    <Edge cubics="!31 652(;31,652 42,653 42,653q31 652 42 653);"/>
                    <Edge cubics="!60 653(;60,653 49,653 49,653q60 653 49 653);"/>
                    <Edge cubics="!60 653(;60,653 91,654 91,654q60 653 91 654);"/>
                    <Edge cubics="!39 623(;39,623 34,626 34,626q39 623 34 626);"/>
                    <Edge cubics="!98 610(;98,610 63,641 63,641q98 610 63 641);"/>
                    <Edge cubics="!29 645(;28,644 26,644 23,644q29 645Q27 644q23 644);"/>
                    <Edge cubics="!19 617(;20,614 23,611 26,608q19 617Q21 613q26 608);"/>
                    <Edge cubics="!20 643(;20,643 31,652 31,652q20 643 31 652);"/>
                    <Edge cubics="!6 624(;9,622 12,619 15,616q6 624Q11 621q15 616);"/>
                    <Edge cubics="!15 616(;15,616 16,615 16,615q15 616 16 615);"/>
                    <Edge cubics="!16 615(;16,615 16,616 16,616q16 615 16 616);"/>
                    <Edge cubics="!1 627(;1,627 1,627 0,627q1 627Q1 627q0 627);"/>
                    <Edge cubics="!6 624(;5,625 3,626 1,627q6 624Q4 625q1 627);"/>
                    <Edge cubics="!57 599(;57,599 6,624 6,624q57 599 6 624);"/>
                    <Edge cubics="!41 594(;41,594 16,615 16,615q41 594 16 615);"/>
                    <Edge cubics="!367 374(;367,374 368,377 368,377q367 374 368 377);"/>
                    <Edge cubics="!26 608(;23,610 19,613 16,616q26 608Q21 611q16 616);"/>
                    <Edge cubics="!49 653(;49,653 42,653 42,653q49 653 42 653);"/>
                    <Edge cubics="!220 117(;219,116 219,116 218,115q220 117Q219 116q218 115);"/>
                    <Edge cubics="!223 138(;222,135 220,132 218,129q223 138Q221 133q218 129);"/>
                    <Edge cubics="!218 115(;218,115 218,129 218,129q218 115 218 129);"/>
                    <Edge cubics="!368 379(;368,383 368,387 368,391q368 379Q368 385q368 391);"/>
                    <Edge cubics="!368 379(;368,384 369,388 370,393q368 379Q368 386q370 393);"/>
                    <Edge cubics="!368 377(;368,377 368,379 368,379q368 377 368 379);"/>
                  </edges>
                </DOMShape>
              </elements>
            </DOMFrame>
          </frames>
        </DOMLayer>
      </layers>
    </DOMTimeline>
  </timeline>
</DOMSymbolItem>